Workbook

Sheet ⚙️ Settings
B2: ⚙️ Settings — goals & master data
B3: Light-blue cells are yours. Custom categories flow into every sheet automatically.
B5: 🎯 GOALS & SETUP
B6: Work days per week | D6: 6 | E6: Drives lunch, commute, deep-work formulas.
B7: Sleep goal (hours per night) | D7: 7.5 | E7: Feeds the Balance Score & sleep warnings.
B8: Weekly productive target (h) | D8: 45 | E8: Goal-progress measures against this.
B9: ⏱️ CONSTANTS
B10: Hours per day | D10: 24
B11: Hours per week | D11: =D10*7 -> 168
B12: Weeks per month | D12: 4
B13: Weeks per year | D13: 52
B15: 🗂️ MASTER CATEGORY TABLE
C16: Category | D16: Ideal h/wk | E16: % of week | F16: Per day | G16: Productive | H16: Min h/wk | I16: Max h/wk | J16: Status
B17: 😴 | C17: Sleep | D17: ='🌟 Ideal Week'!$F$13 -> 57.166667 | E17: =IF($C17="","",$D17/'⚙️ Settings'!$D$11) -> 0.34027778 | F17: =IF($C17="","",$D17/7) -> 8.1666667 | G17: =FALSE() -> FALSE | H17: 49 | I17: 63 | J17: =IF($C17="","",IF(AND($H17<>"",$D17<$H17),"🔻 Low",IF(AND($I17<>"",$D17>$I17),"🔺 High","✅ OK"))) -> ✅ OK
B18: 💼 | C18: Work | D18: ='🌟 Ideal Week'!$F$23 -> 23 | E18: =IF($C18="","",$D18/'⚙️ Settings'!$D$11) -> 0.13690476 | F18: =IF($C18="","",$D18/7) -> 3.2857143 | G18: =TRUE() -> TRUE | I18: 40 | J18: =IF($C18="","",IF(AND($H18<>"",$D18<$H18),"🔻 Low",IF(AND($I18<>"",$D18>$I18),"🔺 High","✅ OK"))) -> ✅ OK
B19: 🎯 | C19: Deep Work | D19: ='🌟 Ideal Week'!$F$28 -> 12 | E19: =IF($C19="","",$D19/'⚙️ Settings'!$D$11) -> 0.071428571 | F19: =IF($C19="","",$D19/7) -> 1.7142857 | G19: =TRUE() -> TRUE | H19: 5 | J19: =IF($C19="","",IF(AND($H19<>"",$D19<$H19),"🔻 Low",IF(AND($I19<>"",$D19>$I19),"🔺 High","✅ OK"))) -> ✅ OK
B20: 🗣️ | C20: Meetings | D20: ='🌟 Ideal Week'!$F$33 -> 5 | E20: =IF($C20="","",$D20/'⚙️ Settings'!$D$11) -> 0.029761905 | F20: =IF($C20="","",$D20/7) -> 0.71428571 | G20: =TRUE() -> TRUE | I20: 15 | J20: =IF($C20="","",IF(AND($H20<>"",$D20<$H20),"🔻 Low",IF(AND($I20<>"",$D20>$I20),"🔺 High","✅ OK"))) -> ✅ OK
B21: 🍕 | C21: Food | D21: ='🌟 Ideal Week'!$F$40 -> 5.9166667 | E21: =IF($C21="","",$D21/'⚙️ Settings'!$D$11) -> 0.035218254 | F21: =IF($C21="","",$D21/7) -> 0.8452381 | G21: =FALSE() -> FALSE | H21: 3.5 | I21: 21 | J21: =IF($C21="","",IF(AND($H21<>"",$D21<$H21),"🔻 Low",IF(AND($I21<>"",$D21>$I21),"🔺 High","✅ OK"))) -> ✅ OK
B22: 🧹 | C22: Household Chores | D22: ='🌟 Ideal Week'!$F$49 -> 4 | E22: =IF($C22="","",$D22/'⚙️ Settings'!$D$11) -> 0.023809524 | F22: =IF($C22="","",$D22/7) -> 0.57142857 | G22: =FALSE() -> FALSE | I22: 15 | J22: =IF($C22="","",IF(AND($H22<>"",$D22<$H22),"🔻 Low",IF(AND($I22<>"",$D22>$I22),"🔺 High","✅ OK"))) -> ✅ OK
B23: 👶 | C23: Childcare | D23: ='🌟 Ideal Week'!$F$56 -> 0 | E23: =IF($C23="","",$D23/'⚙️ Settings'!$D$11) -> 0 | F23: =IF($C23="","",$D23/7) -> 0 | G23: =FALSE() -> FALSE | J23: =IF($C23="","",IF(AND($H23<>"",$D23<$H23),"🔻 Low",IF(AND($I23<>"",$D23>$I23),"🔺 High","✅ OK"))) -> ✅ OK
B24: 🏋️ | C24: Fitness | D24: ='🌟 Ideal Week'!$F$62 -> 10 | E24: =IF($C24="","",$D24/'⚙️ Settings'!$D$11) -> 0.05952381 | F24: =IF($C24="","",$D24/7) -> 1.4285714 | G24: =TRUE() -> TRUE | H24: 3 | I24: 20 | J24: =IF($C24="","",IF(AND($H24<>"",$D24<$H24),"🔻 Low",IF(AND($I24<>"",$D24>$I24),"🔺 High","✅ OK"))) -> ✅ OK
B25: 📺 | C25: Entertainment | D25: ='🌟 Ideal Week'!$F$70 -> 12 | E25: =IF($C25="","",$D25/'⚙️ Settings'!$D$11) -> 0.071428571 | F25: =IF($C25="","",$D25/7) -> 1.7142857 | G25: =FALSE() -> FALSE | I25: 25 | J25: =IF($C25="","",IF(AND($H25<>"",$D25<$H25),"🔻 Low",IF(AND($I25<>"",$D25>$I25),"🔺 High","✅ OK"))) -> ✅ OK
B26: ❤️ | C26: Relationships | D26: ='🌟 Ideal Week'!$F$76 -> 6 | E26: =IF($C26="","",$D26/'⚙️ Settings'!$D$11) -> 0.035714286 | F26: =IF($C26="","",$D26/7) -> 0.85714286 | G26: =FALSE() -> FALSE | H26: 3 | J26: =IF($C26="","",IF(AND($H26<>"",$D26<$H26),"🔻 Low",IF(AND($I26<>"",$D26>$I26),"🔺 High","✅ OK"))) -> ✅ OK
B27: 📚 | C27: Learning | D27: ='🌟 Ideal Week'!$F$83 -> 4.3333333 | E27: =IF($C27="","",$D27/'⚙️ Settings'!$D$11) -> 0.025793651 | F27: =IF($C27="","",$D27/7) -> 0.61904762 | G27: =TRUE() -> TRUE | H27: 1 | J27: =IF($C27="","",IF(AND($H27<>"",$D27<$H27),"🔻 Low",IF(AND($I27<>"",$D27>$I27),"🔺 High","✅ OK"))) -> ✅ OK
B28: 🌱 | C28: Personal Development | D28: ='🌟 Ideal Week'!$F$90 -> 3.3333333 | E28: =IF($C28="","",$D28/'⚙️ Settings'!$D$11) -> 0.01984127 | F28: =IF($C28="","",$D28/7) -> 0.47619048 | G28: =TRUE() -> TRUE | H28: 1 | J28: =IF($C28="","",IF(AND($H28<>"",$D28<$H28),"🔻 Low",IF(AND($I28<>"",$D28>$I28),"🔺 High","✅ OK"))) -> ✅ OK
B29: 🙏 | C29: Spiritual | D29: ='🌟 Ideal Week'!$F$96 -> 0 | E29: =IF($C29="","",$D29/'⚙️ Settings'!$D$11) -> 0 | F29: =IF($C29="","",$D29/7) -> 0 | G29: =FALSE() -> FALSE | J29: =IF($C29="","",IF(AND($H29<>"",$D29<$H29),"🔻 Low",IF(AND($I29<>"",$D29>$I29),"🔺 High","✅ OK"))) -> ✅ OK
B30: 🚗 | C30: Travel | D30: ='🌟 Ideal Week'!$F$102 -> 1.5 | E30: =IF($C30="","",$D30/'⚙️ Settings'!$D$11) -> 0.0089285714 | F30: =IF($C30="","",$D30/7) -> 0.21428571 | G30: =FALSE() -> FALSE | J30: =IF($C30="","",IF(AND($H30<>"",$D30<$H30),"🔻 Low",IF(AND($I30<>"",$D30>$I30),"🔺 High","✅ OK"))) -> ✅ OK
B31: 🗂️ | C31: Admin | D31: ='🌟 Ideal Week'!$F$108 -> 2.5 | E31: =IF($C31="","",$D31/'⚙️ Settings'!$D$11) -> 0.014880952 | F31: =IF($C31="","",$D31/7) -> 0.35714286 | G31: =TRUE() -> TRUE | J31: =IF($C31="","",IF(AND($H31<>"",$D31<$H31),"🔻 Low",IF(AND($I31<>"",$D31>$I31),"🔺 High","✅ OK"))) -> ✅ OK
B32: 📈 | C32: Business Development | D32: ='🌟 Ideal Week'!$F$113 -> 4 | E32: =IF($C32="","",$D32/'⚙️ Settings'!$D$11) -> 0.023809524 | F32: =IF($C32="","",$D32/7) -> 0.57142857 | G32: =TRUE() -> TRUE | J32: =IF($C32="","",IF(AND($H32<>"",$D32<$H32),"🔻 Low",IF(AND($I32<>"",$D32>$I32),"🔺 High","✅ OK"))) -> ✅ OK
B33: 🎬 | C33: Content Creation | D33: ='🌟 Ideal Week'!$F$118 -> 6 | E33: =IF($C33="","",$D33/'⚙️ Settings'!$D$11) -> 0.035714286 | F33: =IF($C33="","",$D33/7) -> 0.85714286 | G33: =TRUE() -> TRUE | J33: =IF($C33="","",IF(AND($H33<>"",$D33<$H33),"🔻 Low",IF(AND($I33<>"",$D33>$I33),"🔺 High","✅ OK"))) -> ✅ OK
E34: =IF($C34="","",$D34/'⚙️ Settings'!$D$11) | F34: =IF($C34="","",$D34/7) | G34: =FALSE() -> FALSE | J34: =IF($C34="","",IF(AND($H34<>"",$D34<$H34),"🔻 Low",IF(AND($I34<>"",$D34>$I34),"🔺 High","✅ OK")))
E35: =IF($C35="","",$D35/'⚙️ Settings'!$D$11) | F35: =IF($C35="","",$D35/7) | G35: =FALSE() -> FALSE | J35: =IF($C35="","",IF(AND($H35<>"",$D35<$H35),"🔻 Low",IF(AND($I35<>"",$D35>$I35),"🔺 High","✅ OK")))
E36: =IF($C36="","",$D36/'⚙️ Settings'!$D$11) | F36: =IF($C36="","",$D36/7) | G36: =FALSE() -> FALSE | J36: =IF($C36="","",IF(AND($H36<>"",$D36<$H36),"🔻 Low",IF(AND($I36<>"",$D36>$I36),"🔺 High","✅ OK")))
E37: =IF($C37="","",$D37/'⚙️ Settings'!$D$11) | F37: =IF($C37="","",$D37/7) | G37: =FALSE() -> FALSE | J37: =IF($C37="","",IF(AND($H37<>"",$D37<$H37),"🔻 Low",IF(AND($I37<>"",$D37>$I37),"🔺 High","✅ OK")))
E38: =IF($C38="","",$D38/'⚙️ Settings'!$D$11) | F38: =IF($C38="","",$D38/7) | G38: =FALSE() -> FALSE | J38: =IF($C38="","",IF(AND($H38<>"",$D38<$H38),"🔻 Low",IF(AND($I38<>"",$D38>$I38),"🔺 High","✅ OK")))
C40: Total allocated | D40: =SUM(D17:D38) -> 156.75
C41: Free time (168 − allocated) | D41: ='⚙️ Settings'!$D$11-D40 -> 11.25
C42: Productive hours | D42: =SUMPRODUCT(--(G17:G38=TRUE()),D17:D38) -> 70.166667

Sheet 🌟 Ideal Week
B2: 🌟 Ideal Week — design your 168 hours
B3: Only edit the light-blue cells. Every sheet in the OS measures reality against this design.
B4: HOURS USED | C4: REMAINING | D4: WEEKLY HRS | E4: MONTHLY HRS | F4: ANNUAL HRS | G4: PRODUCTIVE | H4: FREE TIME | I4: UTILIZATION | J4: BALANCE
B5: ='⚙️ Settings'!$D$40 -> 156.75 | C5: =MAX(0,'⚙️ Settings'!$D$11-SUMIFS('📅 Daily Tracker'!$F$10:$F$159,'📅 Daily Tracker'!$B$10:$B$159,">="&'📆 Current Week'!$M$9,'📅 Daily Tracker'!$B$10:$B$159,"<"&('📆 Current Week'!$M$9+7))) -> 168 | D5: ='⚙️ Settings'!$D$11 -> 168 | E5: ='⚙️ Settings'!$D$40*'⚙️ Settings'!$D$12 -> 627 | F5: ='⚙️ Settings'!$D$40*'⚙️ Settings'!$D$13 -> 8151 | G5: ='⚙️ Settings'!$D$42 -> 70.166667 | H5: ='⚙️ Settings'!$D$41 -> 11.25 | I5: ='⚙️ Settings'!$D$40/'⚙️ Settings'!$D$11 -> 0.93303571 | J5: =ROUND(100*(('⚙️ Settings'!$D$17>='⚙️ Settings'!$D$7*7*0.95)*('⚙️ Settings'!$D$17<=63)+(('⚙️ Settings'!$D$18+'⚙️ Settings'!$D$19+'⚙️ Settings'!$D$20)<=55)*1+('⚙️ Settings'!$D$24>=3)*1+('⚙️ Settings'!$D$26>=3)*1+(('⚙️ Settings'!$D$27+'⚙️ Settings'!$D$28)>=2)*1+('⚙️ Settings'!$D$41>=5)*1+('⚙️ Settings'!$D$41>=0)*1)/7,0) -> 100
B6: ="⏱ Logged — today: "&TEXT(SUMIFS('📅 Daily Tracker'!$F$10:$F$159,'📅 Daily Tracker'!$B$10:$B$159,TODAY()),"0.0")&" h · this week: "&TEXT(SUMIFS('📅 Daily Tracker'!$F$10:$F$159,'📅 Daily Tracker'!$B$10:$B$159,">="&'📆 Current Week'!$M$9,'📅 Daily Tracker'!$B$10:$B$159,"<"&('📆 Current Week'!$M$9+7)),"0.0")&" h · this month: "&TEXT(SUMIFS('📅 Daily Tracker'!$F$10:$F$159,'📅 Daily Tracker'!$B$10:$B$159,">="&EOMONTH(TODAY(),-1)+1,'📅 Daily Tracker'!$B$10:$B$159,"<="&EOMONTH(TODAY(),0)),"0.0")&" h · this year: "&TEXT(SUMIFS('📅 Daily Tracker'!$F$10:$F$159,'📅 Daily Tracker'!$B$10:$B$159,">="&DATE(YEAR(TODAY()),1,1)),"0.0")&" h" -> ⏱ Logged — today: 0.0 h · this week: 0.0 h · this month: 0.0 h · this year: 0.0 h
B9: 😴 SLEEP
B10: I sleep for around | C10: 8 | D10: hours per night. | E10: This means I spend | F10: =C10*7 -> 56 | G10: hours per week sleeping.
B11: I wind down for | C11: 10 | D11: minutes before sleeping. | E11: This means I spend | F11: =C11*7/60 -> 1.1666667 | G11: hours per week preparing to sleep.
B12: My wake-up routine takes | C12: 0 | D12: minutes each morning. | E12: This means I spend | F12: =C12*7/60 -> 0 | G12: hours per week waking up.
E13: 😴 In total, I spend | F13: =F10+F11+F12 -> 57.166667 | G13: ="hours per week on sleep-related things. ≈ "&TEXT($F$13*'⚙️ Settings'!$D$12,"0")&" h/month · "&TEXT($F$13*'⚙️ Settings'!$D$13,"0")&" h/year · "&TEXT($F$13/'⚙️ Settings'!$D$11,"0.0%")&" of your week" -> hours per week on sleep-related things. ≈ 229 h/month · 2973 h/year · 34.0% of your week
E14: ✅ That leaves me with | F14: ='⚙️ Settings'!$D$11-F13 -> 110.83333 | G14: hours per week for everything else.
B16: 💼 WORK
B17: I work | C17: ='⚙️ Settings'!$D$6 -> 6 | D17: days per week (change in ⚙️ Settings).
B18: Outside meetings & deep work, general work takes me | C18: 3 | D18: hours per working day. | E18: This means I spend | F18: =C18*'⚙️ Settings'!$D$6 -> 18 | G18: hours per week on general work.
B19: My lunch break is | C19: 30 | D19: minutes per working day. | E19: This means I spend | F19: =C19*'⚙️ Settings'!$D$6/60 -> 3 | G19: hours per week on my lunch break.
B20: My commute is | C20: 0 | D20: minutes each way. | E20: This means I spend | F20: =C20*2*'⚙️ Settings'!$D$6/60 -> 0 | G20: hours per week commuting.
B21: Getting ready for work takes | C21: 10 | D21: minutes per working day. | E21: This means I spend | F21: =C21*'⚙️ Settings'!$D$6/60 -> 1 | G21: hours per week getting ready.
B22: Switching off after work takes | C22: 10 | D22: minutes per working day. | E22: This means I spend | F22: =C22*'⚙️ Settings'!$D$6/60 -> 1 | G22: hours per week switching off.
E23: 💼 In total, I spend | F23: =F18+F19+F20+F21+F22 -> 23 | G23: ="hours per week working. ≈ "&TEXT($F$23*'⚙️ Settings'!$D$12,"0")&" h/month · "&TEXT($F$23*'⚙️ Settings'!$D$13,"0")&" h/year · "&TEXT($F$23/'⚙️ Settings'!$D$11,"0.0%")&" of your week" -> hours per week working. ≈ 92 h/month · 1196 h/year · 13.7% of your week
E24: ✅ That leaves me with | F24: =F14-F23 -> 87.833333 | G24: hours per week for everything else.
B26: 🎯 DEEP WORK
B27: I do | C27: 2 | D27: hours of deep, focused work per working day. | E27: This means I spend | F27: =C27*'⚙️ Settings'!$D$6 -> 12 | G27: hours per week in deep work.
E28: 🎯 In total, I spend | F28: =F27 -> 12 | G28: ="hours per week of deep work. ≈ "&TEXT($F$28*'⚙️ Settings'!$D$12,"0")&" h/month · "&TEXT($F$28*'⚙️ Settings'!$D$13,"0")&" h/year · "&TEXT($F$28/'⚙️ Settings'!$D$11,"0.0%")&" of your week" -> hours per week of deep work. ≈ 48 h/month · 624 h/year · 7.1% of your week
E29: ✅ That leaves me with | F29: =F24-F28 -> 75.833333 | G29: hours per week for everything else.
B31: 🗣️ MEETINGS
B32: I spend | C32: 5 | D32: hours in meetings per week. | E32: This means I spend | F32: =C32 -> 5 | G32: hours per week in meetings.
E33: 🗣️ In total, I spend | F33: =F32 -> 5 | G33: ="hours per week in meetings. ≈ "&TEXT($F$33*'⚙️ Settings'!$D$12,"0")&" h/month · "&TEXT($F$33*'⚙️ Settings'!$D$13,"0")&" h/year · "&TEXT($F$33/'⚙️ Settings'!$D$11,"0.0%")&" of your week" -> hours per week in meetings. ≈ 20 h/month · 260 h/year · 3.0% of your week
E34: ✅ That leaves me with | F34: =F29-F33 -> 70.833333 | G34: hours per week for everything else.
B36: 🍕 FOOD
B37: Breakfast takes | C37: 15 | D37: minutes per day (eating + prep). | E37: This means I spend | F37: =C37*7/60 -> 1.75 | G37: hours per week on breakfast.
B38: Lunch takes | C38: 40 | D38: minutes per non-working day. | E38: This means I spend | F38: =C38*(7-'⚙️ Settings'!$D$6)/60 -> 0.66666667 | G38: hours per week on lunch (non-work days).
B39: Dinner takes | C39: 30 | D39: minutes per day (eating + prep). | E39: This means I spend | F39: =C39*7/60 -> 3.5 | G39: hours per week on dinner.
E40: 🍕 In total, I spend | F40: =F37+F38+F39 -> 5.9166667 | G40: ="hours per week on food. ≈ "&TEXT($F$40*'⚙️ Settings'!$D$12,"0")&" h/month · "&TEXT($F$40*'⚙️ Settings'!$D$13,"0")&" h/year · "&TEXT($F$40/'⚙️ Settings'!$D$11,"0.0%")&" of your week" -> hours per week on food. ≈ 24 h/month · 308 h/year · 3.5% of your week
E41: ✅ That leaves me with | F41: =F34-F40 -> 64.916667 | G41: hours per week for everything else.
B43: 🧹 HOUSEHOLD CHORES
B44: I do groceries | C44: 2 | D44: times per week.
B45: Each grocery run takes | C45: 60 | D45: minutes (incl. travel). | E45: This means I spend | F45: =C44*C45/60 -> 2 | G45: hours per week on groceries.
B46: I clean the house | C46: 1 | D46: times per week.
B47: Each cleaning session takes | C47: 60 | D47: minutes. | E47: This means I spend | F47: =C46*C47/60 -> 1 | G47: hours per week on cleaning.
B48: Other misc. chores take | C48: 1 | D48: hours per week. | E48: This means I spend | F48: =C48 -> 1 | G48: hours per week on misc. chores.
E49: 🧹 In total, I spend | F49: =F45+F47+F48 -> 4 | G49: ="hours per week on chores. ≈ "&TEXT($F$49*'⚙️ Settings'!$D$12,"0")&" h/month · "&TEXT($F$49*'⚙️ Settings'!$D$13,"0")&" h/year · "&TEXT($F$49/'⚙️ Settings'!$D$11,"0.0%")&" of your week" -> hours per week on chores. ≈ 16 h/month · 208 h/year · 2.4% of your week
E50: ✅ That leaves me with | F50: =F41-F49 -> 60.916667 | G50: hours per week for everything else.
B52: 👶 CHILDCARE
B53: Each weekday I spend | C53: 0 | D53: hours actively on childcare. | E53: This means I spend | F53: =C53*5 -> 0 | G53: hours on weekdays on childcare.
B54: Each weekend day I spend | C54: 0 | D54: hours actively on childcare. | E54: This means I spend | F54: =C54*2 -> 0 | G54: hours on weekends on childcare.
B55: Child admin & logistics take | C55: 0 | D55: hours per week. | E55: This means I spend | F55: =C55 -> 0 | G55: hours per week on child admin.
E56: 👶 In total, I spend | F56: =F53+F54+F55 -> 0 | G56: ="hours per week on childcare. ≈ "&TEXT($F$56*'⚙️ Settings'!$D$12,"0")&" h/month · "&TEXT($F$56*'⚙️ Settings'!$D$13,"0")&" h/year · "&TEXT($F$56/'⚙️ Settings'!$D$11,"0.0%")&" of your week" -> hours per week on childcare. ≈ 0 h/month · 0 h/year · 0.0% of your week
E57: ✅ That leaves me with | F57: =F50-F56 -> 60.916667 | G57: hours per week for everything else.
B59: 🏋️ FITNESS
B60: Each week, I spend | C60: 8 | D60: hours exercising (incl. commute time). | E60: This means I spend | F60: =C60 -> 8 | G60: hours per week exercising.
B61: Each week, I spend | C61: 2 | D61: hours on other fitness-related things. | E61: This means I spend | F61: =C61 -> 2 | G61: hours per week on other fitness.
E62: 🏋️ In total, I spend | F62: =F60+F61 -> 10 | G62: ="hours per week on fitness. ≈ "&TEXT($F$62*'⚙️ Settings'!$D$12,"0")&" h/month · "&TEXT($F$62*'⚙️ Settings'!$D$13,"0")&" h/year · "&TEXT($F$62/'⚙️ Settings'!$D$11,"0.0%")&" of your week" -> hours per week on fitness. ≈ 40 h/month · 520 h/year · 6.0% of your week
E63: ✅ That leaves me with | F63: =F57-F62 -> 50.916667 | G63: hours per week for everything else.
B65: 📺 ENTERTAINMENT
B66: Each week, I spend | C66: 0 | D66: hours watching TV shows / movies. | E66: This means I spend | F66: =C66 -> 0 | G66: hours per week on TV / movies.
B67: Each week, I spend | C67: 7 | D67: hours on social media apps. | E67: This means I spend | F67: =C67 -> 7 | G67: hours per week on social media.
B68: Each week, I spend | C68: 2 | D68: hours reading. | E68: This means I spend | F68: =C68 -> 2 | G68: hours per week reading.
B69: Each week, I spend | C69: 3 | D69: hours on other entertainment. | E69: This means I spend | F69: =C69 -> 3 | G69: hours per week on other entertainment.
E70: 📺 In total, I spend | F70: =F66+F67+F68+F69 -> 12 | G70: ="hours per week on entertainment. ≈ "&TEXT($F$70*'⚙️ Settings'!$D$12,"0")&" h/month · "&TEXT($F$70*'⚙️ Settings'!$D$13,"0")&" h/year · "&TEXT($F$70/'⚙️ Settings'!$D$11,"0.0%")&" of your week" -> hours per week on entertainment. ≈ 48 h/month · 624 h/year · 7.1% of your week
E71: ✅ That leaves me with | F71: =F63-F70 -> 38.916667 | G71: hours per week for everything else.
B73: ❤️ RELATIONSHIPS
B74: Each week, I spend | C74: 3 | D74: hours on quality family time. | E74: This means I spend | F74: =C74 -> 3 | G74: hours per week on family time.
B75: Each week, I spend | C75: 3 | D75: hours on other socialising time. | E75: This means I spend | F75: =C75 -> 3 | G75: hours per week socialising.
E76: ❤️ In total, I spend | F76: =F74+F75 -> 6 | G76: ="hours per week on relationships. ≈ "&TEXT($F$76*'⚙️ Settings'!$D$12,"0")&" h/month · "&TEXT($F$76*'⚙️ Settings'!$D$13,"0")&" h/year · "&TEXT($F$76/'⚙️ Settings'!$D$11,"0.0%")&" of your week" -> hours per week on relationships. ≈ 24 h/month · 312 h/year · 3.6% of your week
E77: ✅ That leaves me with | F77: =F71-F76 -> 32.916667 | G77: hours per week for everything else.
B79: 📚 LEARNING
B80: Courses & structured learning take | C80: 1 | D80: hours per week. | E80: This means I spend | F80: =C80 -> 1 | G80: hours per week on courses.
B81: Books, articles & study take | C81: 1 | D81: hours per week. | E81: This means I spend | F81: =C81 -> 1 | G81: hours per week studying.
B82: I listen to podcasts / audiobooks for | C82: 20 | D82: minutes per day. | E82: This means I spend | F82: =C82*7/60 -> 2.3333333 | G82: hours per week on podcasts.
E83: 📚 In total, I spend | F83: =F80+F81+F82 -> 4.3333333 | G83: ="hours per week on learning. ≈ "&TEXT($F$83*'⚙️ Settings'!$D$12,"0")&" h/month · "&TEXT($F$83*'⚙️ Settings'!$D$13,"0")&" h/year · "&TEXT($F$83/'⚙️ Settings'!$D$11,"0.0%")&" of your week" -> hours per week on learning. ≈ 17 h/month · 225 h/year · 2.6% of your week
E84: ✅ That leaves me with | F84: =F77-F83 -> 28.583333 | G84: hours per week for everything else.
B86: 🌱 PERSONAL DEVELOPMENT
B87: I journal for | C87: 10 | D87: minutes per day. | E87: This means I spend | F87: =C87*7/60 -> 1.1666667 | G87: hours per week journaling.
B88: I meditate for | C88: 10 | D88: minutes per day. | E88: This means I spend | F88: =C88*7/60 -> 1.1666667 | G88: hours per week meditating.
B89: Weekly planning & review takes | C89: 1 | D89: hours per week. | E89: This means I spend | F89: =C89 -> 1 | G89: hours per week planning.
E90: 🌱 In total, I spend | F90: =F87+F88+F89 -> 3.3333333 | G90: ="hours per week on personal development. ≈ "&TEXT($F$90*'⚙️ Settings'!$D$12,"0")&" h/month · "&TEXT($F$90*'⚙️ Settings'!$D$13,"0")&" h/year · "&TEXT($F$90/'⚙️ Settings'!$D$11,"0.0%")&" of your week" -> hours per week on personal development. ≈ 13 h/month · 173 h/year · 2.0% of your week
E91: ✅ That leaves me with | F91: =F84-F90 -> 25.25 | G91: hours per week for everything else.
B93: 🙏 SPIRITUAL
B94: Daily practice takes | C94: 0 | D94: minutes per day. | E94: This means I spend | F94: =C94*7/60 -> 0 | G94: hours per week on daily practice.
B95: Services & community take | C95: 0 | D95: hours per week. | E95: This means I spend | F95: =C95 -> 0 | G95: hours per week on services.
E96: 🙏 In total, I spend | F96: =F94+F95 -> 0 | G96: ="hours per week on spiritual life. ≈ "&TEXT($F$96*'⚙️ Settings'!$D$12,"0")&" h/month · "&TEXT($F$96*'⚙️ Settings'!$D$13,"0")&" h/year · "&TEXT($F$96/'⚙️ Settings'!$D$11,"0.0%")&" of your week" -> hours per week on spiritual life. ≈ 0 h/month · 0 h/year · 0.0% of your week
E97: ✅ That leaves me with | F97: =F91-F96 -> 25.25 | G97: hours per week for everything else.
B99: 🚗 TRAVEL
B100: Errands & getting around (non-commute) take | C100: 1.5 | D100: hours per week. | E100: This means I spend | F100: =C100 -> 1.5 | G100: hours per week on errands.
B101: Trips & other travel take | C101: 0 | D101: hours per week. | E101: This means I spend | F101: =C101 -> 0 | G101: hours per week on trips.
E102: 🚗 In total, I spend | F102: =F100+F101 -> 1.5 | G102: ="hours per week travelling. ≈ "&TEXT($F$102*'⚙️ Settings'!$D$12,"0")&" h/month · "&TEXT($F$102*'⚙️ Settings'!$D$13,"0")&" h/year · "&TEXT($F$102/'⚙️ Settings'!$D$11,"0.0%")&" of your week" -> hours per week travelling. ≈ 6 h/month · 78 h/year · 0.9% of your week
E103: ✅ That leaves me with | F103: =F97-F102 -> 23.75 | G103: hours per week for everything else.
B105: 🗂️ ADMIN
B106: Finances, email & life admin take | C106: 2 | D106: hours per week. | E106: This means I spend | F106: =C106 -> 2 | G106: hours per week on life admin.
B107: Appointments & paperwork take | C107: 30 | D107: minutes per week. | E107: This means I spend | F107: =C107/60 -> 0.5 | G107: hours per week on paperwork.
E108: 🗂️ In total, I spend | F108: =F106+F107 -> 2.5 | G108: ="hours per week on admin. ≈ "&TEXT($F$108*'⚙️ Settings'!$D$12,"0")&" h/month · "&TEXT($F$108*'⚙️ Settings'!$D$13,"0")&" h/year · "&TEXT($F$108/'⚙️ Settings'!$D$11,"0.0%")&" of your week" -> hours per week on admin. ≈ 10 h/month · 130 h/year · 1.5% of your week
E109: ✅ That leaves me with | F109: =F103-F108 -> 21.25 | G109: hours per week for everything else.
B111: 📈 BUSINESS DEVELOPMENT
B112: I spend | C112: 4 | D112: hours per week on sales, partnerships & growth. | E112: This means I spend | F112: =C112 -> 4 | G112: hours per week on business development.
E113: 📈 In total, I spend | F113: =F112 -> 4 | G113: ="hours per week on business development. ≈ "&TEXT($F$113*'⚙️ Settings'!$D$12,"0")&" h/month · "&TEXT($F$113*'⚙️ Settings'!$D$13,"0")&" h/year · "&TEXT($F$113/'⚙️ Settings'!$D$11,"0.0%")&" of your week" -> hours per week on business development. ≈ 16 h/month · 208 h/year · 2.4% of your week
E114: ✅ That leaves me with | F114: =F109-F113 -> 17.25 | G114: hours per week for everything else.
B116: 🎬 CONTENT CREATION
B117: I create content for | C117: 6 | D117: hours per week. | E117: This means I spend | F117: =C117 -> 6 | G117: hours per week creating content.
E118: 🎬 In total, I spend | F118: =F117 -> 6 | G118: ="hours per week creating content. ≈ "&TEXT($F$118*'⚙️ Settings'!$D$12,"0")&" h/month · "&TEXT($F$118*'⚙️ Settings'!$D$13,"0")&" h/year · "&TEXT($F$118/'⚙️ Settings'!$D$11,"0.0%")&" of your week" -> hours per week creating content. ≈ 24 h/month · 312 h/year · 3.6% of your week
E119: ✅ That leaves me with | F119: =F114-F118 -> 11.25 | G119: hours per week for everything else.

Sheet 📆 Current Week
B2: 📆 Current Week — plan, then perform
B3: Leave "My plan" blank to use your Ideal Week. Actuals arrive from the 📅 Daily Tracker automatically.
B4: HOURS USED | C4: REMAINING | D4: WEEKLY HRS | E4: MONTHLY HRS | F4: ANNUAL HRS | G4: PRODUCTIVE | H4: FREE TIME | I4: UTILIZATION | J4: BALANCE
B5: ='⚙️ Settings'!$D$40 -> 156.75 | C5: =MAX(0,'⚙️ Settings'!$D$11-SUMIFS('📅 Daily Tracker'!$F$10:$F$159,'📅 Daily Tracker'!$B$10:$B$159,">="&'📆 Current Week'!$M$9,'📅 Daily Tracker'!$B$10:$B$159,"<"&('📆 Current Week'!$M$9+7))) -> 168 | D5: ='⚙️ Settings'!$D$11 -> 168 | E5: ='⚙️ Settings'!$D$40*'⚙️ Settings'!$D$12 -> 627 | F5: ='⚙️ Settings'!$D$40*'⚙️ Settings'!$D$13 -> 8151 | G5: ='⚙️ Settings'!$D$42 -> 70.166667 | H5: ='⚙️ Settings'!$D$41 -> 11.25 | I5: ='⚙️ Settings'!$D$40/'⚙️ Settings'!$D$11 -> 0.93303571 | J5: =ROUND(100*(('⚙️ Settings'!$D$17>='⚙️ Settings'!$D$7*7*0.95)*('⚙️ Settings'!$D$17<=63)+(('⚙️ Settings'!$D$18+'⚙️ Settings'!$D$19+'⚙️ Settings'!$D$20)<=55)*1+('⚙️ Settings'!$D$24>=3)*1+('⚙️ Settings'!$D$26>=3)*1+(('⚙️ Settings'!$D$27+'⚙️ Settings'!$D$28)>=2)*1+('⚙️ Settings'!$D$41>=5)*1+('⚙️ Settings'!$D$41>=0)*1)/7,0) -> 100
B6: ="⏱ Logged — today: "&TEXT(SUMIFS('📅 Daily Tracker'!$F$10:$F$159,'📅 Daily Tracker'!$B$10:$B$159,TODAY()),"0.0")&" h · this week: "&TEXT(SUMIFS('📅 Daily Tracker'!$F$10:$F$159,'📅 Daily Tracker'!$B$10:$B$159,">="&'📆 Current Week'!$M$9,'📅 Daily Tracker'!$B$10:$B$159,"<"&('📆 Current Week'!$M$9+7)),"0.0")&" h · this month: "&TEXT(SUMIFS('📅 Daily Tracker'!$F$10:$F$159,'📅 Daily Tracker'!$B$10:$B$159,">="&EOMONTH(TODAY(),-1)+1,'📅 Daily Tracker'!$B$10:$B$159,"<="&EOMONTH(TODAY(),0)),"0.0")&" h · this year: "&TEXT(SUMIFS('📅 Daily Tracker'!$F$10:$F$159,'📅 Daily Tracker'!$B$10:$B$159,">="&DATE(YEAR(TODAY()),1,1)),"0.0")&" h" -> ⏱ Logged — today: 0.0 h · this week: 0.0 h · this month: 0.0 h · this year: 0.0 h
B9: ="Week of "&TEXT('📆 Current Week'!$M$9,"ddd d mmm")&" – "&TEXT('📆 Current Week'!$M$9+6,"ddd d mmm yyyy") -> Week of Mon 27 Jul – Sun 2 Aug 2026 | L9: starts: | M9: =TODAY()-WEEKDAY(TODAY(),2)+1 -> 46230
B11: Category | C11: Ideal | D11: My plan | E11: Planned | F11: Actual | G11: Variance | H11: Remaining | I11: % of plan
B12: =IF('⚙️ Settings'!C17="","",'⚙️ Settings'!B17&" "&'⚙️ Settings'!C17) -> 😴 Sleep | C12: =IF($B12="","",'⚙️ Settings'!D17) -> 57.166667 | E12: =IF($B12="","",IF($D12="",$C12,$D12)) -> 57.166667 | F12: =IF($B12="","",SUMIFS('📅 Daily Tracker'!$F$10:$F$159,'📅 Daily Tracker'!$D$10:$D$159,'⚙️ Settings'!C17,'📅 Daily Tracker'!$B$10:$B$159,">="&'📆 Current Week'!$M$9,'📅 Daily Tracker'!$B$10:$B$159,"<"&('📆 Current Week'!$M$9+7))) -> 0 | G12: =IF($B12="","",$F12-$E12) -> -57.166667 | H12: =IF($B12="","",MAX(0,$E12-$F12)) -> 57.166667 | I12: =IF(OR($B12="",$E12=0),"",$F12/$E12) -> 0
B13: =IF('⚙️ Settings'!C18="","",'⚙️ Settings'!B18&" "&'⚙️ Settings'!C18) -> 💼 Work | C13: =IF($B13="","",'⚙️ Settings'!D18) -> 23 | E13: =IF($B13="","",IF($D13="",$C13,$D13)) -> 23 | F13: =IF($B13="","",SUMIFS('📅 Daily Tracker'!$F$10:$F$159,'📅 Daily Tracker'!$D$10:$D$159,'⚙️ Settings'!C18,'📅 Daily Tracker'!$B$10:$B$159,">="&'📆 Current Week'!$M$9,'📅 Daily Tracker'!$B$10:$B$159,"<"&('📆 Current Week'!$M$9+7))) -> 0 | G13: =IF($B13="","",$F13-$E13) -> -23 | H13: =IF($B13="","",MAX(0,$E13-$F13)) -> 23 | I13: =IF(OR($B13="",$E13=0),"",$F13/$E13) -> 0
B14: =IF('⚙️ Settings'!C19="","",'⚙️ Settings'!B19&" "&'⚙️ Settings'!C19) -> 🎯 Deep Work | C14: =IF($B14="","",'⚙️ Settings'!D19) -> 12 | E14: =IF($B14="","",IF($D14="",$C14,$D14)) -> 12 | F14: =IF($B14="","",SUMIFS('📅 Daily Tracker'!$F$10:$F$159,'📅 Daily Tracker'!$D$10:$D$159,'⚙️ Settings'!C19,'📅 Daily Tracker'!$B$10:$B$159,">="&'📆 Current Week'!$M$9,'📅 Daily Tracker'!$B$10:$B$159,"<"&('📆 Current Week'!$M$9+7))) -> 0 | G14: =IF($B14="","",$F14-$E14) -> -12 | H14: =IF($B14="","",MAX(0,$E14-$F14)) -> 12 | I14: =IF(OR($B14="",$E14=0),"",$F14/$E14) -> 0
B15: =IF('⚙️ Settings'!C20="","",'⚙️ Settings'!B20&" "&'⚙️ Settings'!C20) -> 🗣️ Meetings | C15: =IF($B15="","",'⚙️ Settings'!D20) -> 5 | E15: =IF($B15="","",IF($D15="",$C15,$D15)) -> 5 | F15: =IF($B15="","",SUMIFS('📅 Daily Tracker'!$F$10:$F$159,'📅 Daily Tracker'!$D$10:$D$159,'⚙️ Settings'!C20,'📅 Daily Tracker'!$B$10:$B$159,">="&'📆 Current Week'!$M$9,'📅 Daily Tracker'!$B$10:$B$159,"<"&('📆 Current Week'!$M$9+7))) -> 0 | G15: =IF($B15="","",$F15-$E15) -> -5 | H15: =IF($B15="","",MAX(0,$E15-$F15)) -> 5 | I15: =IF(OR($B15="",$E15=0),"",$F15/$E15) -> 0
B16: =IF('⚙️ Settings'!C21="","",'⚙️ Settings'!B21&" "&'⚙️ Settings'!C21) -> 🍕 Food | C16: =IF($B16="","",'⚙️ Settings'!D21) -> 5.9166667 | E16: =IF($B16="","",IF($D16="",$C16,$D16)) -> 5.9166667 | F16: =IF($B16="","",SUMIFS('📅 Daily Tracker'!$F$10:$F$159,'📅 Daily Tracker'!$D$10:$D$159,'⚙️ Settings'!C21,'📅 Daily Tracker'!$B$10:$B$159,">="&'📆 Current Week'!$M$9,'📅 Daily Tracker'!$B$10:$B$159,"<"&('📆 Current Week'!$M$9+7))) -> 0 | G16: =IF($B16="","",$F16-$E16) -> -5.9166667 | H16: =IF($B16="","",MAX(0,$E16-$F16)) -> 5.9166667 | I16: =IF(OR($B16="",$E16=0),"",$F16/$E16) -> 0
B17: =IF('⚙️ Settings'!C22="","",'⚙️ Settings'!B22&" "&'⚙️ Settings'!C22) -> 🧹 Household Chores | C17: =IF($B17="","",'⚙️ Settings'!D22) -> 4 | E17: =IF($B17="","",IF($D17="",$C17,$D17)) -> 4 | F17: =IF($B17="","",SUMIFS('📅 Daily Tracker'!$F$10:$F$159,'📅 Daily Tracker'!$D$10:$D$159,'⚙️ Settings'!C22,'📅 Daily Tracker'!$B$10:$B$159,">="&'📆 Current Week'!$M$9,'📅 Daily Tracker'!$B$10:$B$159,"<"&('📆 Current Week'!$M$9+7))) -> 0 | G17: =IF($B17="","",$F17-$E17) -> -4 | H17: =IF($B17="","",MAX(0,$E17-$F17)) -> 4 | I17: =IF(OR($B17="",$E17=0),"",$F17/$E17) -> 0
B18: =IF('⚙️ Settings'!C23="","",'⚙️ Settings'!B23&" "&'⚙️ Settings'!C23) -> 👶 Childcare | C18: =IF($B18="","",'⚙️ Settings'!D23) -> 0 | E18: =IF($B18="","",IF($D18="",$C18,$D18)) -> 0 | F18: =IF($B18="","",SUMIFS('📅 Daily Tracker'!$F$10:$F$159,'📅 Daily Tracker'!$D$10:$D$159,'⚙️ Settings'!C23,'📅 Daily Tracker'!$B$10:$B$159,">="&'📆 Current Week'!$M$9,'📅 Daily Tracker'!$B$10:$B$159,"<"&('📆 Current Week'!$M$9+7))) -> 0 | G18: =IF($B18="","",$F18-$E18) -> 0 | H18: =IF($B18="","",MAX(0,$E18-$F18)) -> 0 | I18: =IF(OR($B18="",$E18=0),"",$F18/$E18)
B19: =IF('⚙️ Settings'!C24="","",'⚙️ Settings'!B24&" "&'⚙️ Settings'!C24) -> 🏋️ Fitness | C19: =IF($B19="","",'⚙️ Settings'!D24) -> 10 | E19: =IF($B19="","",IF($D19="",$C19,$D19)) -> 10 | F19: =IF($B19="","",SUMIFS('📅 Daily Tracker'!$F$10:$F$159,'📅 Daily Tracker'!$D$10:$D$159,'⚙️ Settings'!C24,'📅 Daily Tracker'!$B$10:$B$159,">="&'📆 Current Week'!$M$9,'📅 Daily Tracker'!$B$10:$B$159,"<"&('📆 Current Week'!$M$9+7))) -> 0 | G19: =IF($B19="","",$F19-$E19) -> -10 | H19: =IF($B19="","",MAX(0,$E19-$F19)) -> 10 | I19: =IF(OR($B19="",$E19=0),"",$F19/$E19) -> 0
B20: =IF('⚙️ Settings'!C25="","",'⚙️ Settings'!B25&" "&'⚙️ Settings'!C25) -> 📺 Entertainment | C20: =IF($B20="","",'⚙️ Settings'!D25) -> 12 | E20: =IF($B20="","",IF($D20="",$C20,$D20)) -> 12 | F20: =IF($B20="","",SUMIFS('📅 Daily Tracker'!$F$10:$F$159,'📅 Daily Tracker'!$D$10:$D$159,'⚙️ Settings'!C25,'📅 Daily Tracker'!$B$10:$B$159,">="&'📆 Current Week'!$M$9,'📅 Daily Tracker'!$B$10:$B$159,"<"&('📆 Current Week'!$M$9+7))) -> 0 | G20: =IF($B20="","",$F20-$E20) -> -12 | H20: =IF($B20="","",MAX(0,$E20-$F20)) -> 12 | I20: =IF(OR($B20="",$E20=0),"",$F20/$E20) -> 0
B21: =IF('⚙️ Settings'!C26="","",'⚙️ Settings'!B26&" "&'⚙️ Settings'!C26) -> ❤️ Relationships | C21: =IF($B21="","",'⚙️ Settings'!D26) -> 6 | E21: =IF($B21="","",IF($D21="",$C21,$D21)) -> 6 | F21: =IF($B21="","",SUMIFS('📅 Daily Tracker'!$F$10:$F$159,'📅 Daily Tracker'!$D$10:$D$159,'⚙️ Settings'!C26,'📅 Daily Tracker'!$B$10:$B$159,">="&'📆 Current Week'!$M$9,'📅 Daily Tracker'!$B$10:$B$159,"<"&('📆 Current Week'!$M$9+7))) -> 0 | G21: =IF($B21="","",$F21-$E21) -> -6 | H21: =IF($B21="","",MAX(0,$E21-$F21)) -> 6 | I21: =IF(OR($B21="",$E21=0),"",$F21/$E21) -> 0
B22: =IF('⚙️ Settings'!C27="","",'⚙️ Settings'!B27&" "&'⚙️ Settings'!C27) -> 📚 Learning | C22: =IF($B22="","",'⚙️ Settings'!D27) -> 4.3333333 | E22: =IF($B22="","",IF($D22="",$C22,$D22)) -> 4.3333333 | F22: =IF($B22="","",SUMIFS('📅 Daily Tracker'!$F$10:$F$159,'📅 Daily Tracker'!$D$10:$D$159,'⚙️ Settings'!C27,'📅 Daily Tracker'!$B$10:$B$159,">="&'📆 Current Week'!$M$9,'📅 Daily Tracker'!$B$10:$B$159,"<"&('📆 Current Week'!$M$9+7))) -> 0 | G22: =IF($B22="","",$F22-$E22) -> -4.3333333 | H22: =IF($B22="","",MAX(0,$E22-$F22)) -> 4.3333333 | I22: =IF(OR($B22="",$E22=0),"",$F22/$E22) -> 0
B23: =IF('⚙️ Settings'!C28="","",'⚙️ Settings'!B28&" "&'⚙️ Settings'!C28) -> 🌱 Personal Development | C23: =IF($B23="","",'⚙️ Settings'!D28) -> 3.3333333 | E23: =IF($B23="","",IF($D23="",$C23,$D23)) -> 3.3333333 | F23: =IF($B23="","",SUMIFS('📅 Daily Tracker'!$F$10:$F$159,'📅 Daily Tracker'!$D$10:$D$159,'⚙️ Settings'!C28,'📅 Daily Tracker'!$B$10:$B$159,">="&'📆 Current Week'!$M$9,'📅 Daily Tracker'!$B$10:$B$159,"<"&('📆 Current Week'!$M$9+7))) -> 0 | G23: =IF($B23="","",$F23-$E23) -> -3.3333333 | H23: =IF($B23="","",MAX(0,$E23-$F23)) -> 3.3333333 | I23: =IF(OR($B23="",$E23=0),"",$F23/$E23) -> 0
... B33: =IF('⚙️ Settings'!C38="","",'⚙️ Settings'!B38&" "&'⚙️ Settings'!C38) | C33: =IF($B33="","",'⚙️ Settings'!D38) | E33: =IF($B33="","",IF($D33="",$C33,$D33)) | F33: =IF($B33="","",SUMIFS('📅 Daily Tracker'!$F$10:$F$159,'📅 Daily Tracker'!$D$10:$D$159,'⚙️ Settings'!C38,'📅 Daily Tracker'!$B$10:$B$159,">="&'📆 Current Week'!$M$9,'📅 Daily Tracker'!$B$10:$B$159,"<"&('📆 Current Week'!$M$9+7))) | G33: =IF($B33="","",$F33-$E33) | H33: =IF($B33="","",MAX(0,$E33-$F33)) | I33: =IF(OR($B33="",$E33=0),"",$F33/$E33)
B35: Total planned / logged | E35: =SUM(E12:E33) -> 156.75 | F35: =SUM(F12:F33) -> 0
B36: Free / remaining hours | E36: ='⚙️ Settings'!$D$11-E35 -> 11.25 | F36: ='⚙️ Settings'!$D$11-F35 -> 168
B37: Utilization | E37: =E35/'⚙️ Settings'!$D$11 -> 0.93303571 | F37: =F35/'⚙️ Settings'!$D$11 -> 0

Sheet 📅 Daily Tracker
B2: 📅 Daily Tracker — the execution engine
B3: Log each block: date, category, actual hours, notes. Week, month and year totals build themselves.
B4: HOURS USED | C4: REMAINING | D4: WEEKLY HRS | E4: MONTHLY HRS | F4: ANNUAL HRS | G4: PRODUCTIVE | H4: FREE TIME | I4: UTILIZATION | J4: BALANCE
B5: ='⚙️ Settings'!$D$40 -> 156.75 | C5: =MAX(0,'⚙️ Settings'!$D$11-SUMIFS('📅 Daily Tracker'!$F$10:$F$159,'📅 Daily Tracker'!$B$10:$B$159,">="&'📆 Current Week'!$M$9,'📅 Daily Tracker'!$B$10:$B$159,"<"&('📆 Current Week'!$M$9+7))) -> 168 | D5: ='⚙️ Settings'!$D$11 -> 168 | E5: ='⚙️ Settings'!$D$40*'⚙️ Settings'!$D$12 -> 627 | F5: ='⚙️ Settings'!$D$40*'⚙️ Settings'!$D$13 -> 8151 | G5: ='⚙️ Settings'!$D$42 -> 70.166667 | H5: ='⚙️ Settings'!$D$41 -> 11.25 | I5: ='⚙️ Settings'!$D$40/'⚙️ Settings'!$D$11 -> 0.93303571 | J5: =ROUND(100*(('⚙️ Settings'!$D$17>='⚙️ Settings'!$D$7*7*0.95)*('⚙️ Settings'!$D$17<=63)+(('⚙️ Settings'!$D$18+'⚙️ Settings'!$D$19+'⚙️ Settings'!$D$20)<=55)*1+('⚙️ Settings'!$D$24>=3)*1+('⚙️ Settings'!$D$26>=3)*1+(('⚙️ Settings'!$D$27+'⚙️ Settings'!$D$28)>=2)*1+('⚙️ Settings'!$D$41>=5)*1+('⚙️ Settings'!$D$41>=0)*1)/7,0) -> 100
B6: ="⏱ Logged — today: "&TEXT(SUMIFS('📅 Daily Tracker'!$F$10:$F$159,'📅 Daily Tracker'!$B$10:$B$159,TODAY()),"0.0")&" h · this week: "&TEXT(SUMIFS('📅 Daily Tracker'!$F$10:$F$159,'📅 Daily Tracker'!$B$10:$B$159,">="&'📆 Current Week'!$M$9,'📅 Daily Tracker'!$B$10:$B$159,"<"&('📆 Current Week'!$M$9+7)),"0.0")&" h · this month: "&TEXT(SUMIFS('📅 Daily Tracker'!$F$10:$F$159,'📅 Daily Tracker'!$B$10:$B$159,">="&EOMONTH(TODAY(),-1)+1,'📅 Daily Tracker'!$B$10:$B$159,"<="&EOMONTH(TODAY(),0)),"0.0")&" h · this year: "&TEXT(SUMIFS('📅 Daily Tracker'!$F$10:$F$159,'📅 Daily Tracker'!$B$10:$B$159,">="&DATE(YEAR(TODAY()),1,1)),"0.0")&" h" -> ⏱ Logged — today: 0.0 h · this week: 0.0 h · this month: 0.0 h · this year: 0.0 h
B8: 📅 DAILY LOG | J8: ⚡ TODAY
B9: Date | C9: Day | D9: Category | E9: Plan/day | F9: Actual h | G9: Notes | H9: Prod. | J9: Daily total | K9: =SUMIFS('📅 Daily Tracker'!$F$10:$F$159,'📅 Daily Tracker'!$B$10:$B$159,TODAY()) -> 0
C10: =IF($B10="","",TEXT($B10,"ddd")) | E10: =IF($D10="","",IFERROR(INDEX('📆 Current Week'!$E$12:$E$33,MATCH($D10,'⚙️ Settings'!$C$17:$C$38,0))/7,"")) | H10: =IF($D10="","",IFERROR(INDEX('⚙️ Settings'!$G$17:$G$38,MATCH($D10,'⚙️ Settings'!$C$17:$C$38,0)),FALSE())) | J10: Remaining today | K10: ='⚙️ Settings'!$D$10-SUMIFS('📅 Daily Tracker'!$F$10:$F$159,'📅 Daily Tracker'!$B$10:$B$159,TODAY()) -> 24
C11: =IF($B11="","",TEXT($B11,"ddd")) | E11: =IF($D11="","",IFERROR(INDEX('📆 Current Week'!$E$12:$E$33,MATCH($D11,'⚙️ Settings'!$C$17:$C$38,0))/7,"")) | H11: =IF($D11="","",IFERROR(INDEX('⚙️ Settings'!$G$17:$G$38,MATCH($D11,'⚙️ Settings'!$C$17:$C$38,0)),FALSE())) | J11: Productivity score | K11: =IFERROR(SUMIFS('📅 Daily Tracker'!$F$10:$F$159,'📅 Daily Tracker'!$B$10:$B$159,TODAY(),'📅 Daily Tracker'!$H$10:$H$159,TRUE())/SUMIFS('📅 Daily Tracker'!$F$10:$F$159,'📅 Daily Tracker'!$B$10:$B$159,TODAY()),0) -> 0
C12: =IF($B12="","",TEXT($B12,"ddd")) | E12: =IF($D12="","",IFERROR(INDEX('📆 Current Week'!$E$12:$E$33,MATCH($D12,'⚙️ Settings'!$C$17:$C$38,0))/7,"")) | H12: =IF($D12="","",IFERROR(INDEX('⚙️ Settings'!$G$17:$G$38,MATCH($D12,'⚙️ Settings'!$C$17:$C$38,0)),FALSE()))
C13: =IF($B13="","",TEXT($B13,"ddd")) | E13: =IF($D13="","",IFERROR(INDEX('📆 Current Week'!$E$12:$E$33,MATCH($D13,'⚙️ Settings'!$C$17:$C$38,0))/7,"")) | H13: =IF($D13="","",IFERROR(INDEX('⚙️ Settings'!$G$17:$G$38,MATCH($D13,'⚙️ Settings'!$C$17:$C$38,0)),FALSE())) | J13: 📊 LAST 7 DAYS
C14: =IF($B14="","",TEXT($B14,"ddd")) | E14: =IF($D14="","",IFERROR(INDEX('📆 Current Week'!$E$12:$E$33,MATCH($D14,'⚙️ Settings'!$C$17:$C$38,0))/7,"")) | H14: =IF($D14="","",IFERROR(INDEX('⚙️ Settings'!$G$17:$G$38,MATCH($D14,'⚙️ Settings'!$C$17:$C$38,0)),FALSE())) | J14: Day | K14: Logged | L14: Left | M14: Prod %
C15: =IF($B15="","",TEXT($B15,"ddd")) | E15: =IF($D15="","",IFERROR(INDEX('📆 Current Week'!$E$12:$E$33,MATCH($D15,'⚙️ Settings'!$C$17:$C$38,0))/7,"")) | H15: =IF($D15="","",IFERROR(INDEX('⚙️ Settings'!$G$17:$G$38,MATCH($D15,'⚙️ Settings'!$C$17:$C$38,0)),FALSE())) | J15: =TEXT(TODAY()-0,"ddd d mmm") -> Sun 2 Aug | K15: =SUMIFS('📅 Daily Tracker'!$F$10:$F$159,'📅 Daily Tracker'!$B$10:$B$159,TODAY()-0) -> 0 | L15: ='⚙️ Settings'!$D$10-K15 -> 24 | M15: =IFERROR(SUMIFS('📅 Daily Tracker'!$F$10:$F$159,'📅 Daily Tracker'!$B$10:$B$159,TODAY()-0,'📅 Daily Tracker'!$H$10:$H$159,TRUE())/K15,"")
C16: =IF($B16="","",TEXT($B16,"ddd")) | E16: =IF($D16="","",IFERROR(INDEX('📆 Current Week'!$E$12:$E$33,MATCH($D16,'⚙️ Settings'!$C$17:$C$38,0))/7,"")) | H16: =IF($D16="","",IFERROR(INDEX('⚙️ Settings'!$G$17:$G$38,MATCH($D16,'⚙️ Settings'!$C$17:$C$38,0)),FALSE())) | J16: =TEXT(TODAY()-1,"ddd d mmm") -> Sat 1 Aug | K16: =SUMIFS('📅 Daily Tracker'!$F$10:$F$159,'📅 Daily Tracker'!$B$10:$B$159,TODAY()-1) -> 0 | L16: ='⚙️ Settings'!$D$10-K16 -> 24 | M16: =IFERROR(SUMIFS('📅 Daily Tracker'!$F$10:$F$159,'📅 Daily Tracker'!$B$10:$B$159,TODAY()-1,'📅 Daily Tracker'!$H$10:$H$159,TRUE())/K16,"")
C17: =IF($B17="","",TEXT($B17,"ddd")) | E17: =IF($D17="","",IFERROR(INDEX('📆 Current Week'!$E$12:$E$33,MATCH($D17,'⚙️ Settings'!$C$17:$C$38,0))/7,"")) | H17: =IF($D17="","",IFERROR(INDEX('⚙️ Settings'!$G$17:$G$38,MATCH($D17,'⚙️ Settings'!$C$17:$C$38,0)),FALSE())) | J17: =TEXT(TODAY()-2,"ddd d mmm") -> Fri 31 Jul | K17: =SUMIFS('📅 Daily Tracker'!$F$10:$F$159,'📅 Daily Tracker'!$B$10:$B$159,TODAY()-2) -> 0 | L17: ='⚙️ Settings'!$D$10-K17 -> 24 | M17: =IFERROR(SUMIFS('📅 Daily Tracker'!$F$10:$F$159,'📅 Daily Tracker'!$B$10:$B$159,TODAY()-2,'📅 Daily Tracker'!$H$10:$H$159,TRUE())/K17,"")
C18: =IF($B18="","",TEXT($B18,"ddd")) | E18: =IF($D18="","",IFERROR(INDEX('📆 Current Week'!$E$12:$E$33,MATCH($D18,'⚙️ Settings'!$C$17:$C$38,0))/7,"")) | H18: =IF($D18="","",IFERROR(INDEX('⚙️ Settings'!$G$17:$G$38,MATCH($D18,'⚙️ Settings'!$C$17:$C$38,0)),FALSE())) | J18: =TEXT(TODAY()-3,"ddd d mmm") -> Thu 30 Jul | K18: =SUMIFS('📅 Daily Tracker'!$F$10:$F$159,'📅 Daily Tracker'!$B$10:$B$159,TODAY()-3) -> 0 | L18: ='⚙️ Settings'!$D$10-K18 -> 24 | M18: =IFERROR(SUMIFS('📅 Daily Tracker'!$F$10:$F$159,'📅 Daily Tracker'!$B$10:$B$159,TODAY()-3,'📅 Daily Tracker'!$H$10:$H$159,TRUE())/K18,"")
C19: =IF($B19="","",TEXT($B19,"ddd")) | E19: =IF($D19="","",IFERROR(INDEX('📆 Current Week'!$E$12:$E$33,MATCH($D19,'⚙️ Settings'!$C$17:$C$38,0))/7,"")) | H19: =IF($D19="","",IFERROR(INDEX('⚙️ Settings'!$G$17:$G$38,MATCH($D19,'⚙️ Settings'!$C$17:$C$38,0)),FALSE())) | J19: =TEXT(TODAY()-4,"ddd d mmm") -> Wed 29 Jul | K19: =SUMIFS('📅 Daily Tracker'!$F$10:$F$159,'📅 Daily Tracker'!$B$10:$B$159,TODAY()-4) -> 0 | L19: ='⚙️ Settings'!$D$10-K19 -> 24 | M19: =IFERROR(SUMIFS('📅 Daily Tracker'!$F$10:$F$159,'📅 Daily Tracker'!$B$10:$B$159,TODAY()-4,'📅 Daily Tracker'!$H$10:$H$159,TRUE())/K19,"")
C20: =IF($B20="","",TEXT($B20,"ddd")) | E20: =IF($D20="","",IFERROR(INDEX('📆 Current Week'!$E$12:$E$33,MATCH($D20,'⚙️ Settings'!$C$17:$C$38,0))/7,"")) | H20: =IF($D20="","",IFERROR(INDEX('⚙️ Settings'!$G$17:$G$38,MATCH($D20,'⚙️ Settings'!$C$17:$C$38,0)),FALSE())) | J20: =TEXT(TODAY()-5,"ddd d mmm") -> Tue 28 Jul | K20: =SUMIFS('📅 Daily Tracker'!$F$10:$F$159,'📅 Daily Tracker'!$B$10:$B$159,TODAY()-5) -> 0 | L20: ='⚙️ Settings'!$D$10-K20 -> 24 | M20: =IFERROR(SUMIFS('📅 Daily Tracker'!$F$10:$F$159,'📅 Daily Tracker'!$B$10:$B$159,TODAY()-5,'📅 Daily Tracker'!$H$10:$H$159,TRUE())/K20,"")
C21: =IF($B21="","",TEXT($B21,"ddd")) | E21: =IF($D21="","",IFERROR(INDEX('📆 Current Week'!$E$12:$E$33,MATCH($D21,'⚙️ Settings'!$C$17:$C$38,0))/7,"")) | H21: =IF($D21="","",IFERROR(INDEX('⚙️ Settings'!$G$17:$G$38,MATCH($D21,'⚙️ Settings'!$C$17:$C$38,0)),FALSE())) | J21: =TEXT(TODAY()-6,"ddd d mmm") -> Mon 27 Jul | K21: =SUMIFS('📅 Daily Tracker'!$F$10:$F$159,'📅 Daily Tracker'!$B$10:$B$159,TODAY()-6) -> 0 | L21: ='⚙️ Settings'!$D$10-K21 -> 24 | M21: =IFERROR(SUMIFS('📅 Daily Tracker'!$F$10:$F$159,'📅 Daily Tracker'!$B$10:$B$159,TODAY()-6,'📅 Daily Tracker'!$H$10:$H$159,TRUE())/K21,"")
C22: =IF($B22="","",TEXT($B22,"ddd")) | E22: =IF($D22="","",IFERROR(INDEX('📆 Current Week'!$E$12:$E$33,MATCH($D22,'⚙️ Settings'!$C$17:$C$38,0))/7,"")) | H22: =IF($D22="","",IFERROR(INDEX('⚙️ Settings'!$G$17:$G$38,MATCH($D22,'⚙️ Settings'!$C$17:$C$38,0)),FALSE()))
C23: =IF($B23="","",TEXT($B23,"ddd")) | E23: =IF($D23="","",IFERROR(INDEX('📆 Current Week'!$E$12:$E$33,MATCH($D23,'⚙️ Settings'!$C$17:$C$38,0))/7,"")) | H23: =IF($D23="","",IFERROR(INDEX('⚙️ Settings'!$G$17:$G$38,MATCH($D23,'⚙️ Settings'!$C$17:$C$38,0)),FALSE()))
C24: =IF($B24="","",TEXT($B24,"ddd")) | E24: =IF($D24="","",IFERROR(INDEX('📆 Current Week'!$E$12:$E$33,MATCH($D24,'⚙️ Settings'!$C$17:$C$38,0))/7,"")) | H24: =IF($D24="","",IFERROR(INDEX('⚙️ Settings'!$G$17:$G$38,MATCH($D24,'⚙️ Settings'!$C$17:$C$38,0)),FALSE()))
C25: =IF($B25="","",TEXT($B25,"ddd")) | E25: =IF($D25="","",IFERROR(INDEX('📆 Current Week'!$E$12:$E$33,MATCH($D25,'⚙️ Settings'!$C$17:$C$38,0))/7,"")) | H25: =IF($D25="","",IFERROR(INDEX('⚙️ Settings'!$G$17:$G$38,MATCH($D25,'⚙️ Settings'!$C$17:$C$38,0)),FALSE()))
C26: =IF($B26="","",TEXT($B26,"ddd")) | E26: =IF($D26="","",IFERROR(INDEX('📆 Current Week'!$E$12:$E$33,MATCH($D26,'⚙️ Settings'!$C$17:$C$38,0))/7,"")) | H26: =IF($D26="","",IFERROR(INDEX('⚙️ Settings'!$G$17:$G$38,MATCH($D26,'⚙️ Settings'!$C$17:$C$38,0)),FALSE()))
C27: =IF($B27="","",TEXT($B27,"ddd")) | E27: =IF($D27="","",IFERROR(INDEX('📆 Current Week'!$E$12:$E$33,MATCH($D27,'⚙️ Settings'!$C$17:$C$38,0))/7,"")) | H27: =IF($D27="","",IFERROR(INDEX('⚙️ Settings'!$G$17:$G$38,MATCH($D27,'⚙️ Settings'!$C$17:$C$38,0)),FALSE()))
C28: =IF($B28="","",TEXT($B28,"ddd")) | E28: =IF($D28="","",IFERROR(INDEX('📆 Current Week'!$E$12:$E$33,MATCH($D28,'⚙️ Settings'!$C$17:$C$38,0))/7,"")) | H28: =IF($D28="","",IFERROR(INDEX('⚙️ Settings'!$G$17:$G$38,MATCH($D28,'⚙️ Settings'!$C$17:$C$38,0)),FALSE()))
C29: =IF($B29="","",TEXT($B29,"ddd")) | E29: =IF($D29="","",IFERROR(INDEX('📆 Current Week'!$E$12:$E$33,MATCH($D29,'⚙️ Settings'!$C$17:$C$38,0))/7,"")) | H29: =IF($D29="","",IFERROR(INDEX('⚙️ Settings'!$G$17:$G$38,MATCH($D29,'⚙️ Settings'!$C$17:$C$38,0)),FALSE()))
C30: =IF($B30="","",TEXT($B30,"ddd")) | E30: =IF($D30="","",IFERROR(INDEX('📆 Current Week'!$E$12:$E$33,MATCH($D30,'⚙️ Settings'!$C$17:$C$38,0))/7,"")) | H30: =IF($D30="","",IFERROR(INDEX('⚙️ Settings'!$G$17:$G$38,MATCH($D30,'⚙️ Settings'!$C$17:$C$38,0)),FALSE()))
C31: =IF($B31="","",TEXT($B31,"ddd")) | E31: =IF($D31="","",IFERROR(INDEX('📆 Current Week'!$E$12:$E$33,MATCH($D31,'⚙️ Settings'!$C$17:$C$38,0))/7,"")) | H31: =IF($D31="","",IFERROR(INDEX('⚙️ Settings'!$G$17:$G$38,MATCH($D31,'⚙️ Settings'!$C$17:$C$38,0)),FALSE()))
C32: =IF($B32="","",TEXT($B32,"ddd")) | E32: =IF($D32="","",IFERROR(INDEX('📆 Current Week'!$E$12:$E$33,MATCH($D32,'⚙️ Settings'!$C$17:$C$38,0))/7,"")) | H32: =IF($D32="","",IFERROR(INDEX('⚙️ Settings'!$G$17:$G$38,MATCH($D32,'⚙️ Settings'!$C$17:$C$38,0)),FALSE()))
C33: =IF($B33="","",TEXT($B33,"ddd")) | E33: =IF($D33="","",IFERROR(INDEX('📆 Current Week'!$E$12:$E$33,MATCH($D33,'⚙️ Settings'!$C$17:$C$38,0))/7,"")) | H33: =IF($D33="","",IFERROR(INDEX('⚙️ Settings'!$G$17:$G$38,MATCH($D33,'⚙️ Settings'!$C$17:$C$38,0)),FALSE()))
... C159: =IF($B159="","",TEXT($B159,"ddd")) | E159: =IF($D159="","",IFERROR(INDEX('📆 Current Week'!$E$12:$E$33,MATCH($D159,'⚙️ Settings'!$C$17:$C$38,0))/7,"")) | H159: =IF($D159="","",IFERROR(INDEX('⚙️ Settings'!$G$17:$G$38,MATCH($D159,'⚙️ Settings'!$C$17:$C$38,0)),FALSE()))

Sheet 🗓️ Monthly Review
B2: 🗓️ Monthly Review
B3: Everything derives automatically from the 📅 Daily Tracker log.
B4: HOURS USED | C4: REMAINING | D4: WEEKLY HRS | E4: MONTHLY HRS | F4: ANNUAL HRS | G4: PRODUCTIVE | H4: FREE TIME | I4: UTILIZATION | J4: BALANCE
B5: ='⚙️ Settings'!$D$40 -> 156.75 | C5: =MAX(0,'⚙️ Settings'!$D$11-SUMIFS('📅 Daily Tracker'!$F$10:$F$159,'📅 Daily Tracker'!$B$10:$B$159,">="&'📆 Current Week'!$M$9,'📅 Daily Tracker'!$B$10:$B$159,"<"&('📆 Current Week'!$M$9+7))) -> 168 | D5: ='⚙️ Settings'!$D$11 -> 168 | E5: ='⚙️ Settings'!$D$40*'⚙️ Settings'!$D$12 -> 627 | F5: ='⚙️ Settings'!$D$40*'⚙️ Settings'!$D$13 -> 8151 | G5: ='⚙️ Settings'!$D$42 -> 70.166667 | H5: ='⚙️ Settings'!$D$41 -> 11.25 | I5: ='⚙️ Settings'!$D$40/'⚙️ Settings'!$D$11 -> 0.93303571 | J5: =ROUND(100*(('⚙️ Settings'!$D$17>='⚙️ Settings'!$D$7*7*0.95)*('⚙️ Settings'!$D$17<=63)+(('⚙️ Settings'!$D$18+'⚙️ Settings'!$D$19+'⚙️ Settings'!$D$20)<=55)*1+('⚙️ Settings'!$D$24>=3)*1+('⚙️ Settings'!$D$26>=3)*1+(('⚙️ Settings'!$D$27+'⚙️ Settings'!$D$28)>=2)*1+('⚙️ Settings'!$D$41>=5)*1+('⚙️ Settings'!$D$41>=0)*1)/7,0) -> 100
B6: ="⏱ Logged — today: "&TEXT(SUMIFS('📅 Daily Tracker'!$F$10:$F$159,'📅 Daily Tracker'!$B$10:$B$159,TODAY()),"0.0")&" h · this week: "&TEXT(SUMIFS('📅 Daily Tracker'!$F$10:$F$159,'📅 Daily Tracker'!$B$10:$B$159,">="&'📆 Current Week'!$M$9,'📅 Daily Tracker'!$B$10:$B$159,"<"&('📆 Current Week'!$M$9+7)),"0.0")&" h · this month: "&TEXT(SUMIFS('📅 Daily Tracker'!$F$10:$F$159,'📅 Daily Tracker'!$B$10:$B$159,">="&EOMONTH(TODAY(),-1)+1,'📅 Daily Tracker'!$B$10:$B$159,"<="&EOMONTH(TODAY(),0)),"0.0")&" h · this year: "&TEXT(SUMIFS('📅 Daily Tracker'!$F$10:$F$159,'📅 Daily Tracker'!$B$10:$B$159,">="&DATE(YEAR(TODAY()),1,1)),"0.0")&" h" -> ⏱ Logged — today: 0.0 h · this week: 0.0 h · this month: 0.0 h · this year: 0.0 h
B9: ="Reviewing: "&TEXT(TODAY(),"mmmm yyyy") -> Reviewing: August 2026
B10: 🗓️ MONTHLY SUMMARY | J10: 📆 WEEKLY BREAKDOWN
B11: Category | C11: Ideal h/wk | D11: Ideal month | E11: Actual month | F11: Variance | G11: % of month | H11: Rank | J11: W1 | K11: W2 | L11: W3 | M11: W4 | N11: W5
B12: =IF('⚙️ Settings'!C17="","",'⚙️ Settings'!B17&" "&'⚙️ Settings'!C17) -> 😴 Sleep | C12: =IF($B12="","",'⚙️ Settings'!D17) -> 57.166667 | D12: =IF($B12="","",$C12*'⚙️ Settings'!$D$12) -> 228.66667 | E12: =IF($B12="","",SUMIFS('📅 Daily Tracker'!$F$10:$F$159,'📅 Daily Tracker'!$D$10:$D$159,'⚙️ Settings'!C17,'📅 Daily Tracker'!$B$10:$B$159,">="&EOMONTH(TODAY(),-1)+1,'📅 Daily Tracker'!$B$10:$B$159,"<="&EOMONTH(TODAY(),0))) -> 0 | F12: =IF($B12="","",$E12-$D12) -> -228.66667 | G12: =IF($B12="","",$D12/('⚙️ Settings'!$D$11*'⚙️ Settings'!$D$12)) -> 0.34027778 | H12: =IF(OR($B12="",$E12=0),"",RANK($E12,$E$12:$E$33)) | J12: =IF($B12="","",SUMIFS('📅 Daily Tracker'!$F$10:$F$159,'📅 Daily Tracker'!$D$10:$D$159,'⚙️ Settings'!C17,'📅 Daily Tracker'!$B$10:$B$159,">="&EOMONTH(TODAY(),-1)+1+0,'📅 Daily Tracker'!$B$10:$B$159,"<"&MIN(EOMONTH(TODAY(),0)+1,EOMONTH(TODAY(),-1)+1+7))) -> 0 | K12: =IF($B12="","",SUMIFS('📅 Daily Tracker'!$F$10:$F$159,'📅 Daily Tracker'!$D$10:$D$159,'⚙️ Settings'!C17,'📅 Daily Tracker'!$B$10:$B$159,">="&EOMONTH(TODAY(),-1)+1+7,'📅 Daily Tracker'!$B$10:$B$159,"<"&MIN(EOMONTH(TODAY(),0)+1,EOMONTH(TODAY(),-1)+1+14))) -> 0 | L12: =IF($B12="","",SUMIFS('📅 Daily Tracker'!$F$10:$F$159,'📅 Daily Tracker'!$D$10:$D$159,'⚙️ Settings'!C17,'📅 Daily Tracker'!$B$10:$B$159,">="&EOMONTH(TODAY(),-1)+1+14,'📅 Daily Tracker'!$B$10:$B$159,"<"&MIN(EOMONTH(TODAY(),0)+1,EOMONTH(TODAY(),-1)+1+21))) -> 0 | M12: =IF($B12="","",SUMIFS('📅 Daily Tracker'!$F$10:$F$159,'📅 Daily Tracker'!$D$10:$D$159,'⚙️ Settings'!C17,'📅 Daily Tracker'!$B$10:$B$159,">="&EOMONTH(TODAY(),-1)+1+21,'📅 Daily Tracker'!$B$10:$B$159,"<"&MIN(EOMONTH(TODAY(),0)+1,EOMONTH(TODAY(),-1)+1+28))) -> 0 | N12: =IF($B12="","",SUMIFS('📅 Daily Tracker'!$F$10:$F$159,'📅 Daily Tracker'!$D$10:$D$159,'⚙️ Settings'!C17,'📅 Daily Tracker'!$B$10:$B$159,">="&EOMONTH(TODAY(),-1)+1+28,'📅 Daily Tracker'!$B$10:$B$159,"<"&MIN(EOMONTH(TODAY(),0)+1,EOMONTH(TODAY(),-1)+1+35))) -> 0
B13: =IF('⚙️ Settings'!C18="","",'⚙️ Settings'!B18&" "&'⚙️ Settings'!C18) -> 💼 Work | C13: =IF($B13="","",'⚙️ Settings'!D18) -> 23 | D13: =IF($B13="","",$C13*'⚙️ Settings'!$D$12) -> 92 | E13: =IF($B13="","",SUMIFS('📅 Daily Tracker'!$F$10:$F$159,'📅 Daily Tracker'!$D$10:$D$159,'⚙️ Settings'!C18,'📅 Daily Tracker'!$B$10:$B$159,">="&EOMONTH(TODAY(),-1)+1,'📅 Daily Tracker'!$B$10:$B$159,"<="&EOMONTH(TODAY(),0))) -> 0 | F13: =IF($B13="","",$E13-$D13) -> -92 | G13: =IF($B13="","",$D13/('⚙️ Settings'!$D$11*'⚙️ Settings'!$D$12)) -> 0.13690476 | H13: =IF(OR($B13="",$E13=0),"",RANK($E13,$E$12:$E$33)) | J13: =IF($B13="","",SUMIFS('📅 Daily Tracker'!$F$10:$F$159,'📅 Daily Tracker'!$D$10:$D$159,'⚙️ Settings'!C18,'📅 Daily Tracker'!$B$10:$B$159,">="&EOMONTH(TODAY(),-1)+1+0,'📅 Daily Tracker'!$B$10:$B$159,"<"&MIN(EOMONTH(TODAY(),0)+1,EOMONTH(TODAY(),-1)+1+7))) -> 0 | K13: =IF($B13="","",SUMIFS('📅 Daily Tracker'!$F$10:$F$159,'📅 Daily Tracker'!$D$10:$D$159,'⚙️ Settings'!C18,'📅 Daily Tracker'!$B$10:$B$159,">="&EOMONTH(TODAY(),-1)+1+7,'📅 Daily Tracker'!$B$10:$B$159,"<"&MIN(EOMONTH(TODAY(),0)+1,EOMONTH(TODAY(),-1)+1+14))) -> 0 | L13: =IF($B13="","",SUMIFS('📅 Daily Tracker'!$F$10:$F$159,'📅 Daily Tracker'!$D$10:$D$159,'⚙️ Settings'!C18,'📅 Daily Tracker'!$B$10:$B$159,">="&EOMONTH(TODAY(),-1)+1+14,'📅 Daily Tracker'!$B$10:$B$159,"<"&MIN(EOMONTH(TODAY(),0)+1,EOMONTH(TODAY(),-1)+1+21))) -> 0 | M13: =IF($B13="","",SUMIFS('📅 Daily Tracker'!$F$10:$F$159,'📅 Daily Tracker'!$D$10:$D$159,'⚙️ Settings'!C18,'📅 Daily Tracker'!$B$10:$B$159,">="&EOMONTH(TODAY(),-1)+1+21,'📅 Daily Tracker'!$B$10:$B$159,"<"&MIN(EOMONTH(TODAY(),0)+1,EOMONTH(TODAY(),-1)+1+28))) -> 0 | N13: =IF($B13="","",SUMIFS('📅 Daily Tracker'!$F$10:$F$159,'📅 Daily Tracker'!$D$10:$D$159,'⚙️ Settings'!C18,'📅 Daily Tracker'!$B$10:$B$159,">="&EOMONTH(TODAY(),-1)+1+28,'📅 Daily Tracker'!$B$10:$B$159,"<"&MIN(EOMONTH(TODAY(),0)+1,EOMONTH(TODAY(),-1)+1+35))) -> 0
B14: =IF('⚙️ Settings'!C19="","",'⚙️ Settings'!B19&" "&'⚙️ Settings'!C19) -> 🎯 Deep Work | C14: =IF($B14="","",'⚙️ Settings'!D19) -> 12 | D14: =IF($B14="","",$C14*'⚙️ Settings'!$D$12) -> 48 | E14: =IF($B14="","",SUMIFS('📅 Daily Tracker'!$F$10:$F$159,'📅 Daily Tracker'!$D$10:$D$159,'⚙️ Settings'!C19,'📅 Daily Tracker'!$B$10:$B$159,">="&EOMONTH(TODAY(),-1)+1,'📅 Daily Tracker'!$B$10:$B$159,"<="&EOMONTH(TODAY(),0))) -> 0 | F14: =IF($B14="","",$E14-$D14) -> -48 | G14: =IF($B14="","",$D14/('⚙️ Settings'!$D$11*'⚙️ Settings'!$D$12)) -> 0.071428571 | H14: =IF(OR($B14="",$E14=0),"",RANK($E14,$E$12:$E$33)) | J14: =IF($B14="","",SUMIFS('📅 Daily Tracker'!$F$10:$F$159,'📅 Daily Tracker'!$D$10:$D$159,'⚙️ Settings'!C19,'📅 Daily Tracker'!$B$10:$B$159,">="&EOMONTH(TODAY(),-1)+1+0,'📅 Daily Tracker'!$B$10:$B$159,"<"&MIN(EOMONTH(TODAY(),0)+1,EOMONTH(TODAY(),-1)+1+7))) -> 0 | K14: =IF($B14="","",SUMIFS('📅 Daily Tracker'!$F$10:$F$159,'📅 Daily Tracker'!$D$10:$D$159,'⚙️ Settings'!C19,'📅 Daily Tracker'!$B$10:$B$159,">="&EOMONTH(TODAY(),-1)+1+7,'📅 Daily Tracker'!$B$10:$B$159,"<"&MIN(EOMONTH(TODAY(),0)+1,EOMONTH(TODAY(),-1)+1+14))) -> 0 | L14: =IF($B14="","",SUMIFS('📅 Daily Tracker'!$F$10:$F$159,'📅 Daily Tracker'!$D$10:$D$159,'⚙️ Settings'!C19,'📅 Daily Tracker'!$B$10:$B$159,">="&EOMONTH(TODAY(),-1)+1+14,'📅 Daily Tracker'!$B$10:$B$159,"<"&MIN(EOMONTH(TODAY(),0)+1,EOMONTH(TODAY(),-1)+1+21))) -> 0 | M14: =IF($B14="","",SUMIFS('📅 Daily Tracker'!$F$10:$F$159,'📅 Daily Tracker'!$D$10:$D$159,'⚙️ Settings'!C19,'📅 Daily Tracker'!$B$10:$B$159,">="&EOMONTH(TODAY(),-1)+1+21,'📅 Daily Tracker'!$B$10:$B$159,"<"&MIN(EOMONTH(TODAY(),0)+1,EOMONTH(TODAY(),-1)+1+28))) -> 0 | N14: =IF($B14="","",SUMIFS('📅 Daily Tracker'!$F$10:$F$159,'📅 Daily Tracker'!$D$10:$D$159,'⚙️ Settings'!C19,'📅 Daily Tracker'!$B$10:$B$159,">="&EOMONTH(TODAY(),-1)+1+28,'📅 Daily Tracker'!$B$10:$B$159,"<"&MIN(EOMONTH(TODAY(),0)+1,EOMONTH(TODAY(),-1)+1+35))) -> 0
B15: =IF('⚙️ Settings'!C20="","",'⚙️ Settings'!B20&" "&'⚙️ Settings'!C20) -> 🗣️ Meetings | C15: =IF($B15="","",'⚙️ Settings'!D20) -> 5 | D15: =IF($B15="","",$C15*'⚙️ Settings'!$D$12) -> 20 | E15: =IF($B15="","",SUMIFS('📅 Daily Tracker'!$F$10:$F$159,'📅 Daily Tracker'!$D$10:$D$159,'⚙️ Settings'!C20,'📅 Daily Tracker'!$B$10:$B$159,">="&EOMONTH(TODAY(),-1)+1,'📅 Daily Tracker'!$B$10:$B$159,"<="&EOMONTH(TODAY(),0))) -> 0 | F15: =IF($B15="","",$E15-$D15) -> -20 | G15: =IF($B15="","",$D15/('⚙️ Settings'!$D$11*'⚙️ Settings'!$D$12)) -> 0.029761905 | H15: =IF(OR($B15="",$E15=0),"",RANK($E15,$E$12:$E$33)) | J15: =IF($B15="","",SUMIFS('📅 Daily Tracker'!$F$10:$F$159,'📅 Daily Tracker'!$D$10:$D$159,'⚙️ Settings'!C20,'📅 Daily Tracker'!$B$10:$B$159,">="&EOMONTH(TODAY(),-1)+1+0,'📅 Daily Tracker'!$B$10:$B$159,"<"&MIN(EOMONTH(TODAY(),0)+1,EOMONTH(TODAY(),-1)+1+7))) -> 0 | K15: =IF($B15="","",SUMIFS('📅 Daily Tracker'!$F$10:$F$159,'📅 Daily Tracker'!$D$10:$D$159,'⚙️ Settings'!C20,'📅 Daily Tracker'!$B$10:$B$159,">="&EOMONTH(TODAY(),-1)+1+7,'📅 Daily Tracker'!$B$10:$B$159,"<"&MIN(EOMONTH(TODAY(),0)+1,EOMONTH(TODAY(),-1)+1+14))) -> 0 | L15: =IF($B15="","",SUMIFS('📅 Daily Tracker'!$F$10:$F$159,'📅 Daily Tracker'!$D$10:$D$159,'⚙️ Settings'!C20,'📅 Daily Tracker'!$B$10:$B$159,">="&EOMONTH(TODAY(),-1)+1+14,'📅 Daily Tracker'!$B$10:$B$159,"<"&MIN(EOMONTH(TODAY(),0)+1,EOMONTH(TODAY(),-1)+1+21))) -> 0 | M15: =IF($B15="","",SUMIFS('📅 Daily Tracker'!$F$10:$F$159,'📅 Daily Tracker'!$D$10:$D$159,'⚙️ Settings'!C20,'📅 Daily Tracker'!$B$10:$B$159,">="&EOMONTH(TODAY(),-1)+1+21,'📅 Daily Tracker'!$B$10:$B$159,"<"&MIN(EOMONTH(TODAY(),0)+1,EOMONTH(TODAY(),-1)+1+28))) -> 0 | N15: =IF($B15="","",SUMIFS('📅 Daily Tracker'!$F$10:$F$159,'📅 Daily Tracker'!$D$10:$D$159,'⚙️ Settings'!C20,'📅 Daily Tracker'!$B$10:$B$159,">="&EOMONTH(TODAY(),-1)+1+28,'📅 Daily Tracker'!$B$10:$B$159,"<"&MIN(EOMONTH(TODAY(),0)+1,EOMONTH(TODAY(),-1)+1+35))) -> 0
B16: =IF('⚙️ Settings'!C21="","",'⚙️ Settings'!B21&" "&'⚙️ Settings'!C21) -> 🍕 Food | C16: =IF($B16="","",'⚙️ Settings'!D21) -> 5.9166667 | D16: =IF($B16="","",$C16*'⚙️ Settings'!$D$12) -> 23.666667 | E16: =IF($B16="","",SUMIFS('📅 Daily Tracker'!$F$10:$F$159,'📅 Daily Tracker'!$D$10:$D$159,'⚙️ Settings'!C21,'📅 Daily Tracker'!$B$10:$B$159,">="&EOMONTH(TODAY(),-1)+1,'📅 Daily Tracker'!$B$10:$B$159,"<="&EOMONTH(TODAY(),0))) -> 0 | F16: =IF($B16="","",$E16-$D16) -> -23.666667 | G16: =IF($B16="","",$D16/('⚙️ Settings'!$D$11*'⚙️ Settings'!$D$12)) -> 0.035218254 | H16: =IF(OR($B16="",$E16=0),"",RANK($E16,$E$12:$E$33)) | J16: =IF($B16="","",SUMIFS('📅 Daily Tracker'!$F$10:$F$159,'📅 Daily Tracker'!$D$10:$D$159,'⚙️ Settings'!C21,'📅 Daily Tracker'!$B$10:$B$159,">="&EOMONTH(TODAY(),-1)+1+0,'📅 Daily Tracker'!$B$10:$B$159,"<"&MIN(EOMONTH(TODAY(),0)+1,EOMONTH(TODAY(),-1)+1+7))) -> 0 | K16: =IF($B16="","",SUMIFS('📅 Daily Tracker'!$F$10:$F$159,'📅 Daily Tracker'!$D$10:$D$159,'⚙️ Settings'!C21,'📅 Daily Tracker'!$B$10:$B$159,">="&EOMONTH(TODAY(),-1)+1+7,'📅 Daily Tracker'!$B$10:$B$159,"<"&MIN(EOMONTH(TODAY(),0)+1,EOMONTH(TODAY(),-1)+1+14))) -> 0 | L16: =IF($B16="","",SUMIFS('📅 Daily Tracker'!$F$10:$F$159,'📅 Daily Tracker'!$D$10:$D$159,'⚙️ Settings'!C21,'📅 Daily Tracker'!$B$10:$B$159,">="&EOMONTH(TODAY(),-1)+1+14,'📅 Daily Tracker'!$B$10:$B$159,"<"&MIN(EOMONTH(TODAY(),0)+1,EOMONTH(TODAY(),-1)+1+21))) -> 0 | M16: =IF($B16="","",SUMIFS('📅 Daily Tracker'!$F$10:$F$159,'📅 Daily Tracker'!$D$10:$D$159,'⚙️ Settings'!C21,'📅 Daily Tracker'!$B$10:$B$159,">="&EOMONTH(TODAY(),-1)+1+21,'📅 Daily Tracker'!$B$10:$B$159,"<"&MIN(EOMONTH(TODAY(),0)+1,EOMONTH(TODAY(),-1)+1+28))) -> 0 | N16: =IF($B16="","",SUMIFS('📅 Daily Tracker'!$F$10:$F$159,'📅 Daily Tracker'!$D$10:$D$159,'⚙️ Settings'!C21,'📅 Daily Tracker'!$B$10:$B$159,">="&EOMONTH(TODAY(),-1)+1+28,'📅 Daily Tracker'!$B$10:$B$159,"<"&MIN(EOMONTH(TODAY(),0)+1,EOMONTH(TODAY(),-1)+1+35))) -> 0
B17: =IF('⚙️ Settings'!C22="","",'⚙️ Settings'!B22&" "&'⚙️ Settings'!C22) -> 🧹 Household Chores | C17: =IF($B17="","",'⚙️ Settings'!D22) -> 4 | D17: =IF($B17="","",$C17*'⚙️ Settings'!$D$12) -> 16 | E17: =IF($B17="","",SUMIFS('📅 Daily Tracker'!$F$10:$F$159,'📅 Daily Tracker'!$D$10:$D$159,'⚙️ Settings'!C22,'📅 Daily Tracker'!$B$10:$B$159,">="&EOMONTH(TODAY(),-1)+1,'📅 Daily Tracker'!$B$10:$B$159,"<="&EOMONTH(TODAY(),0))) -> 0 | F17: =IF($B17="","",$E17-$D17) -> -16 | G17: =IF($B17="","",$D17/('⚙️ Settings'!$D$11*'⚙️ Settings'!$D$12)) -> 0.023809524 | H17: =IF(OR($B17="",$E17=0),"",RANK($E17,$E$12:$E$33)) | J17: =IF($B17="","",SUMIFS('📅 Daily Tracker'!$F$10:$F$159,'📅 Daily Tracker'!$D$10:$D$159,'⚙️ Settings'!C22,'📅 Daily Tracker'!$B$10:$B$159,">="&EOMONTH(TODAY(),-1)+1+0,'📅 Daily Tracker'!$B$10:$B$159,"<"&MIN(EOMONTH(TODAY(),0)+1,EOMONTH(TODAY(),-1)+1+7))) -> 0 | K17: =IF($B17="","",SUMIFS('📅 Daily Tracker'!$F$10:$F$159,'📅 Daily Tracker'!$D$10:$D$159,'⚙️ Settings'!C22,'📅 Daily Tracker'!$B$10:$B$159,">="&EOMONTH(TODAY(),-1)+1+7,'📅 Daily Tracker'!$B$10:$B$159,"<"&MIN(EOMONTH(TODAY(),0)+1,EOMONTH(TODAY(),-1)+1+14))) -> 0 | L17: =IF($B17="","",SUMIFS('📅 Daily Tracker'!$F$10:$F$159,'📅 Daily Tracker'!$D$10:$D$159,'⚙️ Settings'!C22,'📅 Daily Tracker'!$B$10:$B$159,">="&EOMONTH(TODAY(),-1)+1+14,'📅 Daily Tracker'!$B$10:$B$159,"<"&MIN(EOMONTH(TODAY(),0)+1,EOMONTH(TODAY(),-1)+1+21))) -> 0 | M17: =IF($B17="","",SUMIFS('📅 Daily Tracker'!$F$10:$F$159,'📅 Daily Tracker'!$D$10:$D$159,'⚙️ Settings'!C22,'📅 Daily Tracker'!$B$10:$B$159,">="&EOMONTH(TODAY(),-1)+1+21,'📅 Daily Tracker'!$B$10:$B$159,"<"&MIN(EOMONTH(TODAY(),0)+1,EOMONTH(TODAY(),-1)+1+28))) -> 0 | N17: =IF($B17="","",SUMIFS('📅 Daily Tracker'!$F$10:$F$159,'📅 Daily Tracker'!$D$10:$D$159,'⚙️ Settings'!C22,'📅 Daily Tracker'!$B$10:$B$159,">="&EOMONTH(TODAY(),-1)+1+28,'📅 Daily Tracker'!$B$10:$B$159,"<"&MIN(EOMONTH(TODAY(),0)+1,EOMONTH(TODAY(),-1)+1+35))) -> 0
B18: =IF('⚙️ Settings'!C23="","",'⚙️ Settings'!B23&" "&'⚙️ Settings'!C23) -> 👶 Childcare | C18: =IF($B18="","",'⚙️ Settings'!D23) -> 0 | D18: =IF($B18="","",$C18*'⚙️ Settings'!$D$12) -> 0 | E18: =IF($B18="","",SUMIFS('📅 Daily Tracker'!$F$10:$F$159,'📅 Daily Tracker'!$D$10:$D$159,'⚙️ Settings'!C23,'📅 Daily Tracker'!$B$10:$B$159,">="&EOMONTH(TODAY(),-1)+1,'📅 Daily Tracker'!$B$10:$B$159,"<="&EOMONTH(TODAY(),0))) -> 0 | F18: =IF($B18="","",$E18-$D18) -> 0 | G18: =IF($B18="","",$D18/('⚙️ Settings'!$D$11*'⚙️ Settings'!$D$12)) -> 0 | H18: =IF(OR($B18="",$E18=0),"",RANK($E18,$E$12:$E$33)) | J18: =IF($B18="","",SUMIFS('📅 Daily Tracker'!$F$10:$F$159,'📅 Daily Tracker'!$D$10:$D$159,'⚙️ Settings'!C23,'📅 Daily Tracker'!$B$10:$B$159,">="&EOMONTH(TODAY(),-1)+1+0,'📅 Daily Tracker'!$B$10:$B$159,"<"&MIN(EOMONTH(TODAY(),0)+1,EOMONTH(TODAY(),-1)+1+7))) -> 0 | K18: =IF($B18="","",SUMIFS('📅 Daily Tracker'!$F$10:$F$159,'📅 Daily Tracker'!$D$10:$D$159,'⚙️ Settings'!C23,'📅 Daily Tracker'!$B$10:$B$159,">="&EOMONTH(TODAY(),-1)+1+7,'📅 Daily Tracker'!$B$10:$B$159,"<"&MIN(EOMONTH(TODAY(),0)+1,EOMONTH(TODAY(),-1)+1+14))) -> 0 | L18: =IF($B18="","",SUMIFS('📅 Daily Tracker'!$F$10:$F$159,'📅 Daily Tracker'!$D$10:$D$159,'⚙️ Settings'!C23,'📅 Daily Tracker'!$B$10:$B$159,">="&EOMONTH(TODAY(),-1)+1+14,'📅 Daily Tracker'!$B$10:$B$159,"<"&MIN(EOMONTH(TODAY(),0)+1,EOMONTH(TODAY(),-1)+1+21))) -> 0 | M18: =IF($B18="","",SUMIFS('📅 Daily Tracker'!$F$10:$F$159,'📅 Daily Tracker'!$D$10:$D$159,'⚙️ Settings'!C23,'📅 Daily Tracker'!$B$10:$B$159,">="&EOMONTH(TODAY(),-1)+1+21,'📅 Daily Tracker'!$B$10:$B$159,"<"&MIN(EOMONTH(TODAY(),0)+1,EOMONTH(TODAY(),-1)+1+28))) -> 0 | N18: =IF($B18="","",SUMIFS('📅 Daily Tracker'!$F$10:$F$159,'📅 Daily Tracker'!$D$10:$D$159,'⚙️ Settings'!C23,'📅 Daily Tracker'!$B$10:$B$159,">="&EOMONTH(TODAY(),-1)+1+28,'📅 Daily Tracker'!$B$10:$B$159,"<"&MIN(EOMONTH(TODAY(),0)+1,EOMONTH(TODAY(),-1)+1+35))) -> 0
B19: =IF('⚙️ Settings'!C24="","",'⚙️ Settings'!B24&" "&'⚙️ Settings'!C24) -> 🏋️ Fitness | C19: =IF($B19="","",'⚙️ Settings'!D24) -> 10 | D19: =IF($B19="","",$C19*'⚙️ Settings'!$D$12) -> 40 | E19: =IF($B19="","",SUMIFS('📅 Daily Tracker'!$F$10:$F$159,'📅 Daily Tracker'!$D$10:$D$159,'⚙️ Settings'!C24,'📅 Daily Tracker'!$B$10:$B$159,">="&EOMONTH(TODAY(),-1)+1,'📅 Daily Tracker'!$B$10:$B$159,"<="&EOMONTH(TODAY(),0))) -> 0 | F19: =IF($B19="","",$E19-$D19) -> -40 | G19: =IF($B19="","",$D19/('⚙️ Settings'!$D$11*'⚙️ Settings'!$D$12)) -> 0.05952381 | H19: =IF(OR($B19="",$E19=0),"",RANK($E19,$E$12:$E$33)) | J19: =IF($B19="","",SUMIFS('📅 Daily Tracker'!$F$10:$F$159,'📅 Daily Tracker'!$D$10:$D$159,'⚙️ Settings'!C24,'📅 Daily Tracker'!$B$10:$B$159,">="&EOMONTH(TODAY(),-1)+1+0,'📅 Daily Tracker'!$B$10:$B$159,"<"&MIN(EOMONTH(TODAY(),0)+1,EOMONTH(TODAY(),-1)+1+7))) -> 0 | K19: =IF($B19="","",SUMIFS('📅 Daily Tracker'!$F$10:$F$159,'📅 Daily Tracker'!$D$10:$D$159,'⚙️ Settings'!C24,'📅 Daily Tracker'!$B$10:$B$159,">="&EOMONTH(TODAY(),-1)+1+7,'📅 Daily Tracker'!$B$10:$B$159,"<"&MIN(EOMONTH(TODAY(),0)+1,EOMONTH(TODAY(),-1)+1+14))) -> 0 | L19: =IF($B19="","",SUMIFS('📅 Daily Tracker'!$F$10:$F$159,'📅 Daily Tracker'!$D$10:$D$159,'⚙️ Settings'!C24,'📅 Daily Tracker'!$B$10:$B$159,">="&EOMONTH(TODAY(),-1)+1+14,'📅 Daily Tracker'!$B$10:$B$159,"<"&MIN(EOMONTH(TODAY(),0)+1,EOMONTH(TODAY(),-1)+1+21))) -> 0 | M19: =IF($B19="","",SUMIFS('📅 Daily Tracker'!$F$10:$F$159,'📅 Daily Tracker'!$D$10:$D$159,'⚙️ Settings'!C24,'📅 Daily Tracker'!$B$10:$B$159,">="&EOMONTH(TODAY(),-1)+1+21,'📅 Daily Tracker'!$B$10:$B$159,"<"&MIN(EOMONTH(TODAY(),0)+1,EOMONTH(TODAY(),-1)+1+28))) -> 0 | N19: =IF($B19="","",SUMIFS('📅 Daily Tracker'!$F$10:$F$159,'📅 Daily Tracker'!$D$10:$D$159,'⚙️ Settings'!C24,'📅 Daily Tracker'!$B$10:$B$159,">="&EOMONTH(TODAY(),-1)+1+28,'📅 Daily Tracker'!$B$10:$B$159,"<"&MIN(EOMONTH(TODAY(),0)+1,EOMONTH(TODAY(),-1)+1+35))) -> 0
B20: =IF('⚙️ Settings'!C25="","",'⚙️ Settings'!B25&" "&'⚙️ Settings'!C25) -> 📺 Entertainment | C20: =IF($B20="","",'⚙️ Settings'!D25) -> 12 | D20: =IF($B20="","",$C20*'⚙️ Settings'!$D$12) -> 48 | E20: =IF($B20="","",SUMIFS('📅 Daily Tracker'!$F$10:$F$159,'📅 Daily Tracker'!$D$10:$D$159,'⚙️ Settings'!C25,'📅 Daily Tracker'!$B$10:$B$159,">="&EOMONTH(TODAY(),-1)+1,'📅 Daily Tracker'!$B$10:$B$159,"<="&EOMONTH(TODAY(),0))) -> 0 | F20: =IF($B20="","",$E20-$D20) -> -48 | G20: =IF($B20="","",$D20/('⚙️ Settings'!$D$11*'⚙️ Settings'!$D$12)) -> 0.071428571 | H20: =IF(OR($B20="",$E20=0),"",RANK($E20,$E$12:$E$33)) | J20: =IF($B20="","",SUMIFS('📅 Daily Tracker'!$F$10:$F$159,'📅 Daily Tracker'!$D$10:$D$159,'⚙️ Settings'!C25,'📅 Daily Tracker'!$B$10:$B$159,">="&EOMONTH(TODAY(),-1)+1+0,'📅 Daily Tracker'!$B$10:$B$159,"<"&MIN(EOMONTH(TODAY(),0)+1,EOMONTH(TODAY(),-1)+1+7))) -> 0 | K20: =IF($B20="","",SUMIFS('📅 Daily Tracker'!$F$10:$F$159,'📅 Daily Tracker'!$D$10:$D$159,'⚙️ Settings'!C25,'📅 Daily Tracker'!$B$10:$B$159,">="&EOMONTH(TODAY(),-1)+1+7,'📅 Daily Tracker'!$B$10:$B$159,"<"&MIN(EOMONTH(TODAY(),0)+1,EOMONTH(TODAY(),-1)+1+14))) -> 0 | L20: =IF($B20="","",SUMIFS('📅 Daily Tracker'!$F$10:$F$159,'📅 Daily Tracker'!$D$10:$D$159,'⚙️ Settings'!C25,'📅 Daily Tracker'!$B$10:$B$159,">="&EOMONTH(TODAY(),-1)+1+14,'📅 Daily Tracker'!$B$10:$B$159,"<"&MIN(EOMONTH(TODAY(),0)+1,EOMONTH(TODAY(),-1)+1+21))) -> 0 | M20: =IF($B20="","",SUMIFS('📅 Daily Tracker'!$F$10:$F$159,'📅 Daily Tracker'!$D$10:$D$159,'⚙️ Settings'!C25,'📅 Daily Tracker'!$B$10:$B$159,">="&EOMONTH(TODAY(),-1)+1+21,'📅 Daily Tracker'!$B$10:$B$159,"<"&MIN(EOMONTH(TODAY(),0)+1,EOMONTH(TODAY(),-1)+1+28))) -> 0 | N20: =IF($B20="","",SUMIFS('📅 Daily Tracker'!$F$10:$F$159,'📅 Daily Tracker'!$D$10:$D$159,'⚙️ Settings'!C25,'📅 Daily Tracker'!$B$10:$B$159,">="&EOMONTH(TODAY(),-1)+1+28,'📅 Daily Tracker'!$B$10:$B$159,"<"&MIN(EOMONTH(TODAY(),0)+1,EOMONTH(TODAY(),-1)+1+35))) -> 0
B21: =IF('⚙️ Settings'!C26="","",'⚙️ Settings'!B26&" "&'⚙️ Settings'!C26) -> ❤️ Relationships | C21: =IF($B21="","",'⚙️ Settings'!D26) -> 6 | D21: =IF($B21="","",$C21*'⚙️ Settings'!$D$12) -> 24 | E21: =IF($B21="","",SUMIFS('📅 Daily Tracker'!$F$10:$F$159,'📅 Daily Tracker'!$D$10:$D$159,'⚙️ Settings'!C26,'📅 Daily Tracker'!$B$10:$B$159,">="&EOMONTH(TODAY(),-1)+1,'📅 Daily Tracker'!$B$10:$B$159,"<="&EOMONTH(TODAY(),0))) -> 0 | F21: =IF($B21="","",$E21-$D21) -> -24 | G21: =IF($B21="","",$D21/('⚙️ Settings'!$D$11*'⚙️ Settings'!$D$12)) -> 0.035714286 | H21: =IF(OR($B21="",$E21=0),"",RANK($E21,$E$12:$E$33)) | J21: =IF($B21="","",SUMIFS('📅 Daily Tracker'!$F$10:$F$159,'📅 Daily Tracker'!$D$10:$D$159,'⚙️ Settings'!C26,'📅 Daily Tracker'!$B$10:$B$159,">="&EOMONTH(TODAY(),-1)+1+0,'📅 Daily Tracker'!$B$10:$B$159,"<"&MIN(EOMONTH(TODAY(),0)+1,EOMONTH(TODAY(),-1)+1+7))) -> 0 | K21: =IF($B21="","",SUMIFS('📅 Daily Tracker'!$F$10:$F$159,'📅 Daily Tracker'!$D$10:$D$159,'⚙️ Settings'!C26,'📅 Daily Tracker'!$B$10:$B$159,">="&EOMONTH(TODAY(),-1)+1+7,'📅 Daily Tracker'!$B$10:$B$159,"<"&MIN(EOMONTH(TODAY(),0)+1,EOMONTH(TODAY(),-1)+1+14))) -> 0 | L21: =IF($B21="","",SUMIFS('📅 Daily Tracker'!$F$10:$F$159,'📅 Daily Tracker'!$D$10:$D$159,'⚙️ Settings'!C26,'📅 Daily Tracker'!$B$10:$B$159,">="&EOMONTH(TODAY(),-1)+1+14,'📅 Daily Tracker'!$B$10:$B$159,"<"&MIN(EOMONTH(TODAY(),0)+1,EOMONTH(TODAY(),-1)+1+21))) -> 0 | M21: =IF($B21="","",SUMIFS('📅 Daily Tracker'!$F$10:$F$159,'📅 Daily Tracker'!$D$10:$D$159,'⚙️ Settings'!C26,'📅 Daily Tracker'!$B$10:$B$159,">="&EOMONTH(TODAY(),-1)+1+21,'📅 Daily Tracker'!$B$10:$B$159,"<"&MIN(EOMONTH(TODAY(),0)+1,EOMONTH(TODAY(),-1)+1+28))) -> 0 | N21: =IF($B21="","",SUMIFS('📅 Daily Tracker'!$F$10:$F$159,'📅 Daily Tracker'!$D$10:$D$159,'⚙️ Settings'!C26,'📅 Daily Tracker'!$B$10:$B$159,">="&EOMONTH(TODAY(),-1)+1+28,'📅 Daily Tracker'!$B$10:$B$159,"<"&MIN(EOMONTH(TODAY(),0)+1,EOMONTH(TODAY(),-1)+1+35))) -> 0
B22: =IF('⚙️ Settings'!C27="","",'⚙️ Settings'!B27&" "&'⚙️ Settings'!C27) -> 📚 Learning | C22: =IF($B22="","",'⚙️ Settings'!D27) -> 4.3333333 | D22: =IF($B22="","",$C22*'⚙️ Settings'!$D$12) -> 17.333333 | E22: =IF($B22="","",SUMIFS('📅 Daily Tracker'!$F$10:$F$159,'📅 Daily Tracker'!$D$10:$D$159,'⚙️ Settings'!C27,'📅 Daily Tracker'!$B$10:$B$159,">="&EOMONTH(TODAY(),-1)+1,'📅 Daily Tracker'!$B$10:$B$159,"<="&EOMONTH(TODAY(),0))) -> 0 | F22: =IF($B22="","",$E22-$D22) -> -17.333333 | G22: =IF($B22="","",$D22/('⚙️ Settings'!$D$11*'⚙️ Settings'!$D$12)) -> 0.025793651 | H22: =IF(OR($B22="",$E22=0),"",RANK($E22,$E$12:$E$33)) | J22: =IF($B22="","",SUMIFS('📅 Daily Tracker'!$F$10:$F$159,'📅 Daily Tracker'!$D$10:$D$159,'⚙️ Settings'!C27,'📅 Daily Tracker'!$B$10:$B$159,">="&EOMONTH(TODAY(),-1)+1+0,'📅 Daily Tracker'!$B$10:$B$159,"<"&MIN(EOMONTH(TODAY(),0)+1,EOMONTH(TODAY(),-1)+1+7))) -> 0 | K22: =IF($B22="","",SUMIFS('📅 Daily Tracker'!$F$10:$F$159,'📅 Daily Tracker'!$D$10:$D$159,'⚙️ Settings'!C27,'📅 Daily Tracker'!$B$10:$B$159,">="&EOMONTH(TODAY(),-1)+1+7,'📅 Daily Tracker'!$B$10:$B$159,"<"&MIN(EOMONTH(TODAY(),0)+1,EOMONTH(TODAY(),-1)+1+14))) -> 0 | L22: =IF($B22="","",SUMIFS('📅 Daily Tracker'!$F$10:$F$159,'📅 Daily Tracker'!$D$10:$D$159,'⚙️ Settings'!C27,'📅 Daily Tracker'!$B$10:$B$159,">="&EOMONTH(TODAY(),-1)+1+14,'📅 Daily Tracker'!$B$10:$B$159,"<"&MIN(EOMONTH(TODAY(),0)+1,EOMONTH(TODAY(),-1)+1+21))) -> 0 | M22: =IF($B22="","",SUMIFS('📅 Daily Tracker'!$F$10:$F$159,'📅 Daily Tracker'!$D$10:$D$159,'⚙️ Settings'!C27,'📅 Daily Tracker'!$B$10:$B$159,">="&EOMONTH(TODAY(),-1)+1+21,'📅 Daily Tracker'!$B$10:$B$159,"<"&MIN(EOMONTH(TODAY(),0)+1,EOMONTH(TODAY(),-1)+1+28))) -> 0 | N22: =IF($B22="","",SUMIFS('📅 Daily Tracker'!$F$10:$F$159,'📅 Daily Tracker'!$D$10:$D$159,'⚙️ Settings'!C27,'📅 Daily Tracker'!$B$10:$B$159,">="&EOMONTH(TODAY(),-1)+1+28,'📅 Daily Tracker'!$B$10:$B$159,"<"&MIN(EOMONTH(TODAY(),0)+1,EOMONTH(TODAY(),-1)+1+35))) -> 0
B23: =IF('⚙️ Settings'!C28="","",'⚙️ Settings'!B28&" "&'⚙️ Settings'!C28) -> 🌱 Personal Development | C23: =IF($B23="","",'⚙️ Settings'!D28) -> 3.3333333 | D23: =IF($B23="","",$C23*'⚙️ Settings'!$D$12) -> 13.333333 | E23: =IF($B23="","",SUMIFS('📅 Daily Tracker'!$F$10:$F$159,'📅 Daily Tracker'!$D$10:$D$159,'⚙️ Settings'!C28,'📅 Daily Tracker'!$B$10:$B$159,">="&EOMONTH(TODAY(),-1)+1,'📅 Daily Tracker'!$B$10:$B$159,"<="&EOMONTH(TODAY(),0))) -> 0 | F23: =IF($B23="","",$E23-$D23) -> -13.333333 | G23: =IF($B23="","",$D23/('⚙️ Settings'!$D$11*'⚙️ Settings'!$D$12)) -> 0.01984127 | H23: =IF(OR($B23="",$E23=0),"",RANK($E23,$E$12:$E$33)) | J23: =IF($B23="","",SUMIFS('📅 Daily Tracker'!$F$10:$F$159,'📅 Daily Tracker'!$D$10:$D$159,'⚙️ Settings'!C28,'📅 Daily Tracker'!$B$10:$B$159,">="&EOMONTH(TODAY(),-1)+1+0,'📅 Daily Tracker'!$B$10:$B$159,"<"&MIN(EOMONTH(TODAY(),0)+1,EOMONTH(TODAY(),-1)+1+7))) -> 0 | K23: =IF($B23="","",SUMIFS('📅 Daily Tracker'!$F$10:$F$159,'📅 Daily Tracker'!$D$10:$D$159,'⚙️ Settings'!C28,'📅 Daily Tracker'!$B$10:$B$159,">="&EOMONTH(TODAY(),-1)+1+7,'📅 Daily Tracker'!$B$10:$B$159,"<"&MIN(EOMONTH(TODAY(),0)+1,EOMONTH(TODAY(),-1)+1+14))) -> 0 | L23: =IF($B23="","",SUMIFS('📅 Daily Tracker'!$F$10:$F$159,'📅 Daily Tracker'!$D$10:$D$159,'⚙️ Settings'!C28,'📅 Daily Tracker'!$B$10:$B$159,">="&EOMONTH(TODAY(),-1)+1+14,'📅 Daily Tracker'!$B$10:$B$159,"<"&MIN(EOMONTH(TODAY(),0)+1,EOMONTH(TODAY(),-1)+1+21))) -> 0 | M23: =IF($B23="","",SUMIFS('📅 Daily Tracker'!$F$10:$F$159,'📅 Daily Tracker'!$D$10:$D$159,'⚙️ Settings'!C28,'📅 Daily Tracker'!$B$10:$B$159,">="&EOMONTH(TODAY(),-1)+1+21,'📅 Daily Tracker'!$B$10:$B$159,"<"&MIN(EOMONTH(TODAY(),0)+1,EOMONTH(TODAY(),-1)+1+28))) -> 0 | N23: =IF($B23="","",SUMIFS('📅 Daily Tracker'!$F$10:$F$159,'📅 Daily Tracker'!$D$10:$D$159,'⚙️ Settings'!C28,'📅 Daily Tracker'!$B$10:$B$159,">="&EOMONTH(TODAY(),-1)+1+28,'📅 Daily Tracker'!$B$10:$B$159,"<"&MIN(EOMONTH(TODAY(),0)+1,EOMONTH(TODAY(),-1)+1+35))) -> 0
... B33: =IF('⚙️ Settings'!C38="","",'⚙️ Settings'!B38&" "&'⚙️ Settings'!C38) | C33: =IF($B33="","",'⚙️ Settings'!D38) | D33: =IF($B33="","",$C33*'⚙️ Settings'!$D$12) | E33: =IF($B33="","",SUMIFS('📅 Daily Tracker'!$F$10:$F$159,'📅 Daily Tracker'!$D$10:$D$159,'⚙️ Settings'!C38,'📅 Daily Tracker'!$B$10:$B$159,">="&EOMONTH(TODAY(),-1)+1,'📅 Daily Tracker'!$B$10:$B$159,"<="&EOMONTH(TODAY(),0))) | F33: =IF($B33="","",$E33-$D33) | G33: =IF($B33="","",$D33/('⚙️ Settings'!$D$11*'⚙️ Settings'!$D$12)) | H33: =IF(OR($B33="",$E33=0),"",RANK($E33,$E$12:$E$33)) | J33: =IF($B33="","",SUMIFS('📅 Daily Tracker'!$F$10:$F$159,'📅 Daily Tracker'!$D$10:$D$159,'⚙️ Settings'!C38,'📅 Daily Tracker'!$B$10:$B$159,">="&EOMONTH(TODAY(),-1)+1+0,'📅 Daily Tracker'!$B$10:$B$159,"<"&MIN(EOMONTH(TODAY(),0)+1,EOMONTH(TODAY(),-1)+1+7))) | K33: =IF($B33="","",SUMIFS('📅 Daily Tracker'!$F$10:$F$159,'📅 Daily Tracker'!$D$10:$D$159,'⚙️ Settings'!C38,'📅 Daily Tracker'!$B$10:$B$159,">="&EOMONTH(TODAY(),-1)+1+7,'📅 Daily Tracker'!$B$10:$B$159,"<"&MIN(EOMONTH(TODAY(),0)+1,EOMONTH(TODAY(),-1)+1+14))) | L33: =IF($B33="","",SUMIFS('📅 Daily Tracker'!$F$10:$F$159,'📅 Daily Tracker'!$D$10:$D$159,'⚙️ Settings'!C38,'📅 Daily Tracker'!$B$10:$B$159,">="&EOMONTH(TODAY(),-1)+1+14,'📅 Daily Tracker'!$B$10:$B$159,"<"&MIN(EOMONTH(TODAY(),0)+1,EOMONTH(TODAY(),-1)+1+21))) | M33: =IF($B33="","",SUMIFS('📅 Daily Tracker'!$F$10:$F$159,'📅 Daily Tracker'!$D$10:$D$159,'⚙️ Settings'!C38,'📅 Daily Tracker'!$B$10:$B$159,">="&EOMONTH(TODAY(),-1)+1+21,'📅 Daily Tracker'!$B$10:$B$159,"<"&MIN(EOMONTH(TODAY(),0)+1,EOMONTH(TODAY(),-1)+1+28))) | N33: =IF($B33="","",SUMIFS('📅 Daily Tracker'!$F$10:$F$159,'📅 Daily Tracker'!$D$10:$D$159,'⚙️ Settings'!C38,'📅 Daily Tracker'!$B$10:$B$159,">="&EOMONTH(TODAY(),-1)+1+28,'📅 Daily Tracker'!$B$10:$B$159,"<"&MIN(EOMONTH(TODAY(),0)+1,EOMONTH(TODAY(),-1)+1+35)))
B35: Total | D35: =SUM(D12:D33) -> 627 | E35: =SUM(E12:E33) -> 0
B37: 💡 MONTHLY INSIGHTS
B38: =IF(SUM($E$12:$E$33)=0,"Log days on the 📅 Daily Tracker to unlock monthly insights.","🏆 Biggest time investment this month: "&INDEX($B$12:$B$33,MATCH(MAX($E$12:$E$33),$E$12:$E$33,0))&" ("&TEXT(MAX($E$12:$E$33),"0.0")&" h logged)") -> Log days on the 📅 Daily Tracker to unlock monthly insights.
B39: =IF(SUM($E$12:$E$33)=0,"",IF(MAX($F$12:$F$33)<=0,"✅ No category is over its monthly plan.","🔺 Most over plan: "&INDEX($B$12:$B$33,MATCH(MAX($F$12:$F$33),$F$12:$F$33,0))&" (+"&TEXT(MAX($F$12:$F$33),"0.0")&" h)"))
B40: =IF(SUM($E$12:$E$33)=0,"","🔻 Most behind plan: "&INDEX($B$12:$B$33,MATCH(MIN($F$12:$F$33),$F$12:$F$33,0))&" ("&TEXT(MIN($F$12:$F$33),"0.0")&" h)")
B41: ="⚖️ Month utilization so far: "&TEXT(SUM($E$12:$E$33)/('⚙️ Settings'!$D$11*'⚙️ Settings'!$D$12),"0.0%")&" of "&ROUND('⚙️ Settings'!$D$11*'⚙️ Settings'!$D$12,0)&" hours." -> ⚖️ Month utilization so far: 0.0% of 672 hours.

Sheet 🎯 Annual Review
B2: 🎯 Annual Review
B3: Ideal Week × 52 versus what you actually logged. Small weekly numbers become life-sized here.
B4: HOURS USED | C4: REMAINING | D4: WEEKLY HRS | E4: MONTHLY HRS | F4: ANNUAL HRS | G4: PRODUCTIVE | H4: FREE TIME | I4: UTILIZATION | J4: BALANCE
B5: ='⚙️ Settings'!$D$40 -> 156.75 | C5: =MAX(0,'⚙️ Settings'!$D$11-SUMIFS('📅 Daily Tracker'!$F$10:$F$159,'📅 Daily Tracker'!$B$10:$B$159,">="&'📆 Current Week'!$M$9,'📅 Daily Tracker'!$B$10:$B$159,"<"&('📆 Current Week'!$M$9+7))) -> 168 | D5: ='⚙️ Settings'!$D$11 -> 168 | E5: ='⚙️ Settings'!$D$40*'⚙️ Settings'!$D$12 -> 627 | F5: ='⚙️ Settings'!$D$40*'⚙️ Settings'!$D$13 -> 8151 | G5: ='⚙️ Settings'!$D$42 -> 70.166667 | H5: ='⚙️ Settings'!$D$41 -> 11.25 | I5: ='⚙️ Settings'!$D$40/'⚙️ Settings'!$D$11 -> 0.93303571 | J5: =ROUND(100*(('⚙️ Settings'!$D$17>='⚙️ Settings'!$D$7*7*0.95)*('⚙️ Settings'!$D$17<=63)+(('⚙️ Settings'!$D$18+'⚙️ Settings'!$D$19+'⚙️ Settings'!$D$20)<=55)*1+('⚙️ Settings'!$D$24>=3)*1+('⚙️ Settings'!$D$26>=3)*1+(('⚙️ Settings'!$D$27+'⚙️ Settings'!$D$28)>=2)*1+('⚙️ Settings'!$D$41>=5)*1+('⚙️ Settings'!$D$41>=0)*1)/7,0) -> 100
B6: ="⏱ Logged — today: "&TEXT(SUMIFS('📅 Daily Tracker'!$F$10:$F$159,'📅 Daily Tracker'!$B$10:$B$159,TODAY()),"0.0")&" h · this week: "&TEXT(SUMIFS('📅 Daily Tracker'!$F$10:$F$159,'📅 Daily Tracker'!$B$10:$B$159,">="&'📆 Current Week'!$M$9,'📅 Daily Tracker'!$B$10:$B$159,"<"&('📆 Current Week'!$M$9+7)),"0.0")&" h · this month: "&TEXT(SUMIFS('📅 Daily Tracker'!$F$10:$F$159,'📅 Daily Tracker'!$B$10:$B$159,">="&EOMONTH(TODAY(),-1)+1,'📅 Daily Tracker'!$B$10:$B$159,"<="&EOMONTH(TODAY(),0)),"0.0")&" h · this year: "&TEXT(SUMIFS('📅 Daily Tracker'!$F$10:$F$159,'📅 Daily Tracker'!$B$10:$B$159,">="&DATE(YEAR(TODAY()),1,1)),"0.0")&" h" -> ⏱ Logged — today: 0.0 h · this week: 0.0 h · this month: 0.0 h · this year: 0.0 h
B8: 🎯 YEAR — PLAN VS REALITY
B9: Category | C9: Weekly h | D9: Annual plan | E9: Actual YTD | F9: On pace | G9: Annual days | H9: % of year | I9: Balance
B10: =IF('⚙️ Settings'!C17="","",'⚙️ Settings'!B17&" "&'⚙️ Settings'!C17) -> 😴 Sleep | C10: =IF($B10="","",'⚙️ Settings'!D17) -> 57.166667 | D10: =IF($B10="","",$C10*'⚙️ Settings'!$D$13) -> 2972.6667 | E10: =IF($B10="","",SUMIFS('📅 Daily Tracker'!$F$10:$F$159,'📅 Daily Tracker'!$D$10:$D$159,'⚙️ Settings'!C17,'📅 Daily Tracker'!$B$10:$B$159,">="&DATE(YEAR(TODAY()),1,1))) -> 0 | F10: =IF(OR($B10="",$C10=0),"",$E10/($C10*MAX(1,ROUNDUP((TODAY()-DATE(YEAR(TODAY()),1,1)+1)/7,0)))) -> 0 | G10: =IF($B10="","",$D10/'⚙️ Settings'!$D$10) -> 123.86111 | H10: =IF($B10="","",$C10/'⚙️ Settings'!$D$11) -> 0.34027778 | I10: =IF($B10="","",'⚙️ Settings'!J17) -> ✅ OK
B11: =IF('⚙️ Settings'!C18="","",'⚙️ Settings'!B18&" "&'⚙️ Settings'!C18) -> 💼 Work | C11: =IF($B11="","",'⚙️ Settings'!D18) -> 23 | D11: =IF($B11="","",$C11*'⚙️ Settings'!$D$13) -> 1196 | E11: =IF($B11="","",SUMIFS('📅 Daily Tracker'!$F$10:$F$159,'📅 Daily Tracker'!$D$10:$D$159,'⚙️ Settings'!C18,'📅 Daily Tracker'!$B$10:$B$159,">="&DATE(YEAR(TODAY()),1,1))) -> 0 | F11: =IF(OR($B11="",$C11=0),"",$E11/($C11*MAX(1,ROUNDUP((TODAY()-DATE(YEAR(TODAY()),1,1)+1)/7,0)))) -> 0 | G11: =IF($B11="","",$D11/'⚙️ Settings'!$D$10) -> 49.833333 | H11: =IF($B11="","",$C11/'⚙️ Settings'!$D$11) -> 0.13690476 | I11: =IF($B11="","",'⚙️ Settings'!J18) -> ✅ OK
B12: =IF('⚙️ Settings'!C19="","",'⚙️ Settings'!B19&" "&'⚙️ Settings'!C19) -> 🎯 Deep Work | C12: =IF($B12="","",'⚙️ Settings'!D19) -> 12 | D12: =IF($B12="","",$C12*'⚙️ Settings'!$D$13) -> 624 | E12: =IF($B12="","",SUMIFS('📅 Daily Tracker'!$F$10:$F$159,'📅 Daily Tracker'!$D$10:$D$159,'⚙️ Settings'!C19,'📅 Daily Tracker'!$B$10:$B$159,">="&DATE(YEAR(TODAY()),1,1))) -> 0 | F12: =IF(OR($B12="",$C12=0),"",$E12/($C12*MAX(1,ROUNDUP((TODAY()-DATE(YEAR(TODAY()),1,1)+1)/7,0)))) -> 0 | G12: =IF($B12="","",$D12/'⚙️ Settings'!$D$10) -> 26 | H12: =IF($B12="","",$C12/'⚙️ Settings'!$D$11) -> 0.071428571 | I12: =IF($B12="","",'⚙️ Settings'!J19) -> ✅ OK
B13: =IF('⚙️ Settings'!C20="","",'⚙️ Settings'!B20&" "&'⚙️ Settings'!C20) -> 🗣️ Meetings | C13: =IF($B13="","",'⚙️ Settings'!D20) -> 5 | D13: =IF($B13="","",$C13*'⚙️ Settings'!$D$13) -> 260 | E13: =IF($B13="","",SUMIFS('📅 Daily Tracker'!$F$10:$F$159,'📅 Daily Tracker'!$D$10:$D$159,'⚙️ Settings'!C20,'📅 Daily Tracker'!$B$10:$B$159,">="&DATE(YEAR(TODAY()),1,1))) -> 0 | F13: =IF(OR($B13="",$C13=0),"",$E13/($C13*MAX(1,ROUNDUP((TODAY()-DATE(YEAR(TODAY()),1,1)+1)/7,0)))) -> 0 | G13: =IF($B13="","",$D13/'⚙️ Settings'!$D$10) -> 10.833333 | H13: =IF($B13="","",$C13/'⚙️ Settings'!$D$11) -> 0.029761905 | I13: =IF($B13="","",'⚙️ Settings'!J20) -> ✅ OK
B14: =IF('⚙️ Settings'!C21="","",'⚙️ Settings'!B21&" "&'⚙️ Settings'!C21) -> 🍕 Food | C14: =IF($B14="","",'⚙️ Settings'!D21) -> 5.9166667 | D14: =IF($B14="","",$C14*'⚙️ Settings'!$D$13) -> 307.66667 | E14: =IF($B14="","",SUMIFS('📅 Daily Tracker'!$F$10:$F$159,'📅 Daily Tracker'!$D$10:$D$159,'⚙️ Settings'!C21,'📅 Daily Tracker'!$B$10:$B$159,">="&DATE(YEAR(TODAY()),1,1))) -> 0 | F14: =IF(OR($B14="",$C14=0),"",$E14/($C14*MAX(1,ROUNDUP((TODAY()-DATE(YEAR(TODAY()),1,1)+1)/7,0)))) -> 0 | G14: =IF($B14="","",$D14/'⚙️ Settings'!$D$10) -> 12.819444 | H14: =IF($B14="","",$C14/'⚙️ Settings'!$D$11) -> 0.035218254 | I14: =IF($B14="","",'⚙️ Settings'!J21) -> ✅ OK
B15: =IF('⚙️ Settings'!C22="","",'⚙️ Settings'!B22&" "&'⚙️ Settings'!C22) -> 🧹 Household Chores | C15: =IF($B15="","",'⚙️ Settings'!D22) -> 4 | D15: =IF($B15="","",$C15*'⚙️ Settings'!$D$13) -> 208 | E15: =IF($B15="","",SUMIFS('📅 Daily Tracker'!$F$10:$F$159,'📅 Daily Tracker'!$D$10:$D$159,'⚙️ Settings'!C22,'📅 Daily Tracker'!$B$10:$B$159,">="&DATE(YEAR(TODAY()),1,1))) -> 0 | F15: =IF(OR($B15="",$C15=0),"",$E15/($C15*MAX(1,ROUNDUP((TODAY()-DATE(YEAR(TODAY()),1,1)+1)/7,0)))) -> 0 | G15: =IF($B15="","",$D15/'⚙️ Settings'!$D$10) -> 8.6666667 | H15: =IF($B15="","",$C15/'⚙️ Settings'!$D$11) -> 0.023809524 | I15: =IF($B15="","",'⚙️ Settings'!J22) -> ✅ OK
B16: =IF('⚙️ Settings'!C23="","",'⚙️ Settings'!B23&" "&'⚙️ Settings'!C23) -> 👶 Childcare | C16: =IF($B16="","",'⚙️ Settings'!D23) -> 0 | D16: =IF($B16="","",$C16*'⚙️ Settings'!$D$13) -> 0 | E16: =IF($B16="","",SUMIFS('📅 Daily Tracker'!$F$10:$F$159,'📅 Daily Tracker'!$D$10:$D$159,'⚙️ Settings'!C23,'📅 Daily Tracker'!$B$10:$B$159,">="&DATE(YEAR(TODAY()),1,1))) -> 0 | F16: =IF(OR($B16="",$C16=0),"",$E16/($C16*MAX(1,ROUNDUP((TODAY()-DATE(YEAR(TODAY()),1,1)+1)/7,0)))) | G16: =IF($B16="","",$D16/'⚙️ Settings'!$D$10) -> 0 | H16: =IF($B16="","",$C16/'⚙️ Settings'!$D$11) -> 0 | I16: =IF($B16="","",'⚙️ Settings'!J23) -> ✅ OK
B17: =IF('⚙️ Settings'!C24="","",'⚙️ Settings'!B24&" "&'⚙️ Settings'!C24) -> 🏋️ Fitness | C17: =IF($B17="","",'⚙️ Settings'!D24) -> 10 | D17: =IF($B17="","",$C17*'⚙️ Settings'!$D$13) -> 520 | E17: =IF($B17="","",SUMIFS('📅 Daily Tracker'!$F$10:$F$159,'📅 Daily Tracker'!$D$10:$D$159,'⚙️ Settings'!C24,'📅 Daily Tracker'!$B$10:$B$159,">="&DATE(YEAR(TODAY()),1,1))) -> 0 | F17: =IF(OR($B17="",$C17=0),"",$E17/($C17*MAX(1,ROUNDUP((TODAY()-DATE(YEAR(TODAY()),1,1)+1)/7,0)))) -> 0 | G17: =IF($B17="","",$D17/'⚙️ Settings'!$D$10) -> 21.666667 | H17: =IF($B17="","",$C17/'⚙️ Settings'!$D$11) -> 0.05952381 | I17: =IF($B17="","",'⚙️ Settings'!J24) -> ✅ OK
B18: =IF('⚙️ Settings'!C25="","",'⚙️ Settings'!B25&" "&'⚙️ Settings'!C25) -> 📺 Entertainment | C18: =IF($B18="","",'⚙️ Settings'!D25) -> 12 | D18: =IF($B18="","",$C18*'⚙️ Settings'!$D$13) -> 624 | E18: =IF($B18="","",SUMIFS('📅 Daily Tracker'!$F$10:$F$159,'📅 Daily Tracker'!$D$10:$D$159,'⚙️ Settings'!C25,'📅 Daily Tracker'!$B$10:$B$159,">="&DATE(YEAR(TODAY()),1,1))) -> 0 | F18: =IF(OR($B18="",$C18=0),"",$E18/($C18*MAX(1,ROUNDUP((TODAY()-DATE(YEAR(TODAY()),1,1)+1)/7,0)))) -> 0 | G18: =IF($B18="","",$D18/'⚙️ Settings'!$D$10) -> 26 | H18: =IF($B18="","",$C18/'⚙️ Settings'!$D$11) -> 0.071428571 | I18: =IF($B18="","",'⚙️ Settings'!J25) -> ✅ OK
B19: =IF('⚙️ Settings'!C26="","",'⚙️ Settings'!B26&" "&'⚙️ Settings'!C26) -> ❤️ Relationships | C19: =IF($B19="","",'⚙️ Settings'!D26) -> 6 | D19: =IF($B19="","",$C19*'⚙️ Settings'!$D$13) -> 312 | E19: =IF($B19="","",SUMIFS('📅 Daily Tracker'!$F$10:$F$159,'📅 Daily Tracker'!$D$10:$D$159,'⚙️ Settings'!C26,'📅 Daily Tracker'!$B$10:$B$159,">="&DATE(YEAR(TODAY()),1,1))) -> 0 | F19: =IF(OR($B19="",$C19=0),"",$E19/($C19*MAX(1,ROUNDUP((TODAY()-DATE(YEAR(TODAY()),1,1)+1)/7,0)))) -> 0 | G19: =IF($B19="","",$D19/'⚙️ Settings'!$D$10) -> 13 | H19: =IF($B19="","",$C19/'⚙️ Settings'!$D$11) -> 0.035714286 | I19: =IF($B19="","",'⚙️ Settings'!J26) -> ✅ OK
B20: =IF('⚙️ Settings'!C27="","",'⚙️ Settings'!B27&" "&'⚙️ Settings'!C27) -> 📚 Learning | C20: =IF($B20="","",'⚙️ Settings'!D27) -> 4.3333333 | D20: =IF($B20="","",$C20*'⚙️ Settings'!$D$13) -> 225.33333 | E20: =IF($B20="","",SUMIFS('📅 Daily Tracker'!$F$10:$F$159,'📅 Daily Tracker'!$D$10:$D$159,'⚙️ Settings'!C27,'📅 Daily Tracker'!$B$10:$B$159,">="&DATE(YEAR(TODAY()),1,1))) -> 0 | F20: =IF(OR($B20="",$C20=0),"",$E20/($C20*MAX(1,ROUNDUP((TODAY()-DATE(YEAR(TODAY()),1,1)+1)/7,0)))) -> 0 | G20: =IF($B20="","",$D20/'⚙️ Settings'!$D$10) -> 9.3888889 | H20: =IF($B20="","",$C20/'⚙️ Settings'!$D$11) -> 0.025793651 | I20: =IF($B20="","",'⚙️ Settings'!J27) -> ✅ OK
B21: =IF('⚙️ Settings'!C28="","",'⚙️ Settings'!B28&" "&'⚙️ Settings'!C28) -> 🌱 Personal Development | C21: =IF($B21="","",'⚙️ Settings'!D28) -> 3.3333333 | D21: =IF($B21="","",$C21*'⚙️ Settings'!$D$13) -> 173.33333 | E21: =IF($B21="","",SUMIFS('📅 Daily Tracker'!$F$10:$F$159,'📅 Daily Tracker'!$D$10:$D$159,'⚙️ Settings'!C28,'📅 Daily Tracker'!$B$10:$B$159,">="&DATE(YEAR(TODAY()),1,1))) -> 0 | F21: =IF(OR($B21="",$C21=0),"",$E21/($C21*MAX(1,ROUNDUP((TODAY()-DATE(YEAR(TODAY()),1,1)+1)/7,0)))) -> 0 | G21: =IF($B21="","",$D21/'⚙️ Settings'!$D$10) -> 7.2222222 | H21: =IF($B21="","",$C21/'⚙️ Settings'!$D$11) -> 0.01984127 | I21: =IF($B21="","",'⚙️ Settings'!J28) -> ✅ OK
... B31: =IF('⚙️ Settings'!C38="","",'⚙️ Settings'!B38&" "&'⚙️ Settings'!C38) | C31: =IF($B31="","",'⚙️ Settings'!D38) | D31: =IF($B31="","",$C31*'⚙️ Settings'!$D$13) | E31: =IF($B31="","",SUMIFS('📅 Daily Tracker'!$F$10:$F$159,'📅 Daily Tracker'!$D$10:$D$159,'⚙️ Settings'!C38,'📅 Daily Tracker'!$B$10:$B$159,">="&DATE(YEAR(TODAY()),1,1))) | F31: =IF(OR($B31="",$C31=0),"",$E31/($C31*MAX(1,ROUNDUP((TODAY()-DATE(YEAR(TODAY()),1,1)+1)/7,0)))) | G31: =IF($B31="","",$D31/'⚙️ Settings'!$D$10) | H31: =IF($B31="","",$C31/'⚙️ Settings'!$D$11) | I31: =IF($B31="","",'⚙️ Settings'!J38)
B33: 📖 YEAR IN REVIEW
B34: ="You have logged "&TEXT(SUM($E$10:$E$31),"#,##0")&" hours so far this year across "&MAX(1,ROUNDUP((TODAY()-DATE(YEAR(TODAY()),1,1)+1)/7,0))&" weeks." -> You have logged 0 hours so far this year across 31 weeks.
B35: =IF(SUM($E$10:$E$31)=0,"Log days on the 📅 Daily Tracker to unlock your Year in Review.","🏆 Your year so far is defined by: "&INDEX($B$10:$B$31,MATCH(MAX($E$10:$E$31),$E$10:$E$31,0))&" ("&TEXT(MAX($E$10:$E$31),"#,##0")&" h logged)") -> Log days on the 📅 Daily Tracker to unlock your Year in Review.
B36: ="😴 At your ideal pace you will sleep "&ROUND('⚙️ Settings'!$D$17*'⚙️ Settings'!$D$13/24,0)&" full days this year." -> 😴 At your ideal pace you will sleep 124 full days this year.
B37: ="💼 Work + deep work + meetings project to "&TEXT(('⚙️ Settings'!$D$18+'⚙️ Settings'!$D$19+'⚙️ Settings'!$D$20)*'⚙️ Settings'!$D$13,"#,##0")&" hours this year." -> 💼 Work + deep work + meetings project to 2,080 hours this year.
B38: ="✅ Free, unallocated time compounds to "&TEXT(MAX(0,'⚙️ Settings'!$D$41)*'⚙️ Settings'!$D$13,"#,##0")&" hours a year. Spend them on purpose." -> ✅ Free, unallocated time compounds to 585 hours a year. Spend them on purpose.

Sheet 📊 Dashboard
B2: ASCENSION OS™ — Executive Dashboard
B3: Read-only command centre. Inputs live on 🌟 Ideal Week, 📆 Current Week and 📅 Daily Tracker. | L3: ="Week "&WEEKNUM(TODAY(),21)&" · "&TEXT(TODAY(),"ddd d mmm yyyy") -> Week 31 · Sun 2 Aug 2026
B4: HOURS USED | C4: REMAINING | D4: WEEKLY HRS | E4: MONTHLY HRS | F4: ANNUAL HRS | G4: PRODUCTIVE | H4: FREE TIME | I4: UTILIZATION | J4: BALANCE
B5: ='⚙️ Settings'!$D$40 -> 156.75 | C5: =MAX(0,'⚙️ Settings'!$D$11-SUMIFS('📅 Daily Tracker'!$F$10:$F$159,'📅 Daily Tracker'!$B$10:$B$159,">="&'📆 Current Week'!$M$9,'📅 Daily Tracker'!$B$10:$B$159,"<"&('📆 Current Week'!$M$9+7))) -> 168 | D5: ='⚙️ Settings'!$D$11 -> 168 | E5: ='⚙️ Settings'!$D$40*'⚙️ Settings'!$D$12 -> 627 | F5: ='⚙️ Settings'!$D$40*'⚙️ Settings'!$D$13 -> 8151 | G5: ='⚙️ Settings'!$D$42 -> 70.166667 | H5: ='⚙️ Settings'!$D$41 -> 11.25 | I5: ='⚙️ Settings'!$D$40/'⚙️ Settings'!$D$11 -> 0.93303571 | J5: =ROUND(100*(('⚙️ Settings'!$D$17>='⚙️ Settings'!$D$7*7*0.95)*('⚙️ Settings'!$D$17<=63)+(('⚙️ Settings'!$D$18+'⚙️ Settings'!$D$19+'⚙️ Settings'!$D$20)<=55)*1+('⚙️ Settings'!$D$24>=3)*1+('⚙️ Settings'!$D$26>=3)*1+(('⚙️ Settings'!$D$27+'⚙️ Settings'!$D$28)>=2)*1+('⚙️ Settings'!$D$41>=5)*1+('⚙️ Settings'!$D$41>=0)*1)/7,0) -> 100
B6: ="⏱ Logged — today: "&TEXT(SUMIFS('📅 Daily Tracker'!$F$10:$F$159,'📅 Daily Tracker'!$B$10:$B$159,TODAY()),"0.0")&" h · this week: "&TEXT(SUMIFS('📅 Daily Tracker'!$F$10:$F$159,'📅 Daily Tracker'!$B$10:$B$159,">="&'📆 Current Week'!$M$9,'📅 Daily Tracker'!$B$10:$B$159,"<"&('📆 Current Week'!$M$9+7)),"0.0")&" h · this month: "&TEXT(SUMIFS('📅 Daily Tracker'!$F$10:$F$159,'📅 Daily Tracker'!$B$10:$B$159,">="&EOMONTH(TODAY(),-1)+1,'📅 Daily Tracker'!$B$10:$B$159,"<="&EOMONTH(TODAY(),0)),"0.0")&" h · this year: "&TEXT(SUMIFS('📅 Daily Tracker'!$F$10:$F$159,'📅 Daily Tracker'!$B$10:$B$159,">="&DATE(YEAR(TODAY()),1,1)),"0.0")&" h" -> ⏱ Logged — today: 0.0 h · this week: 0.0 h · this month: 0.0 h · this year: 0.0 h
B8: 🚦 SIGNALS | L8: LIFE AREA | M8: HOURS
B9: =IF(('⚙️ Settings'!$D$18+'⚙️ Settings'!$D$19+'⚙️ Settings'!$D$20)>60,"🔴 Total work is over 60 h/week — burnout territory.",IF(('⚙️ Settings'!$D$18+'⚙️ Settings'!$D$19+'⚙️ Settings'!$D$20)>55,"🟠 Total work is above 55 h/week — watch the load.","🟢 Work load is sustainable.")) -> 🟢 Work load is sustainable. | L9: 😴 Sleep | M9: ='⚙️ Settings'!D17 -> 57.166667
B10: =IF('⚙️ Settings'!$D$17<'⚙️ Settings'!$D$7*7,"🔴 Sleep is below your nightly goal — recovery first.","🟢 Sleep is on target.") -> 🟢 Sleep is on target. | L10: 💼 Work | M10: ='⚙️ Settings'!D18 -> 23
B11: =IF('⚙️ Settings'!$D$24<3,"🟡 Fitness is under 3 h/week — schedule workouts first.","🟢 Fitness habit is funded.") -> 🟢 Fitness habit is funded. | L11: 🎯 Deep Work | M11: ='⚙️ Settings'!D19 -> 12
B12: =IF('⚙️ Settings'!$D$41<0,"🔴 You allocated MORE than 168 hours — something must give.",IF('⚙️ Settings'!$D$41<5,"🟡 Under 5 h of free time — build in slack.","🟢 Healthy buffer of free time.")) -> 🟢 Healthy buffer of free time. | L12: 🗣️ Meetings | M12: ='⚙️ Settings'!D20 -> 5
B13: =IF('⚙️ Settings'!$D$19<5,"🟡 Deep work is under 5 h/week — protect focus blocks.","🟢 Deep-work practice is funded.") -> 🟢 Deep-work practice is funded. | L13: 🍕 Food | M13: ='⚙️ Settings'!D21 -> 5.9166667
L14: 🧹 Household Chores | M14: ='⚙️ Settings'!D22 -> 4
B15: 🎯 GOAL PROGRESS | L15: 👶 Childcare | M15: ='⚙️ Settings'!D23 -> 0
B16: Goal | C16: Now | D16: Target | E16: % | L16: 🏋️ Fitness | M16: ='⚙️ Settings'!D24 -> 10
B17: Productive hours | C17: ='⚙️ Settings'!$D$42 -> 70.166667 | D17: ='⚙️ Settings'!$D$8 -> 45 | E17: ='⚙️ Settings'!$D$42/'⚙️ Settings'!$D$8 -> 1.5592593 | L17: 📺 Entertainment | M17: ='⚙️ Settings'!D25 -> 12
B18: Sleep (h/week) | C18: ='⚙️ Settings'!$D$17 -> 57.166667 | D18: ='⚙️ Settings'!$D$7*7 -> 52.5 | E18: ='⚙️ Settings'!$D$17/('⚙️ Settings'!$D$7*7) -> 1.0888889 | L18: ❤️ Relationships | M18: ='⚙️ Settings'!D26 -> 6
B19: Free time buffer | C19: =MAX(0,'⚙️ Settings'!$D$41) -> 11.25 | D19: 5 | E19: =MAX(0,'⚙️ Settings'!$D$41)/5 -> 2.25 | L19: 📚 Learning | M19: ='⚙️ Settings'!D27 -> 4.3333333
L20: 🌱 Personal Development | M20: ='⚙️ Settings'!D28 -> 3.3333333
B21: 📈 TRENDS — LOGGED HOURS, LAST 4 WEEKS | L21: 🙏 Spiritual | M21: ='⚙️ Settings'!D29 -> 0
B22: 3 weeks ago | C22: 2 weeks ago | D22: Last week | E22: This week | L22: 🚗 Travel | M22: ='⚙️ Settings'!D30 -> 1.5
B23: =SUMIFS('📅 Daily Tracker'!$F$10:$F$159,'📅 Daily Tracker'!$B$10:$B$159,">="&('📆 Current Week'!$M$9-21),'📅 Daily Tracker'!$B$10:$B$159,"<"&('📆 Current Week'!$M$9-21+7)) -> 0 | C23: =SUMIFS('📅 Daily Tracker'!$F$10:$F$159,'📅 Daily Tracker'!$B$10:$B$159,">="&('📆 Current Week'!$M$9-14),'📅 Daily Tracker'!$B$10:$B$159,"<"&('📆 Current Week'!$M$9-14+7)) -> 0 | D23: =SUMIFS('📅 Daily Tracker'!$F$10:$F$159,'📅 Daily Tracker'!$B$10:$B$159,">="&('📆 Current Week'!$M$9-7),'📅 Daily Tracker'!$B$10:$B$159,"<"&('📆 Current Week'!$M$9-7+7)) -> 0 | E23: =SUMIFS('📅 Daily Tracker'!$F$10:$F$159,'📅 Daily Tracker'!$B$10:$B$159,">="&('📆 Current Week'!$M$9-0),'📅 Daily Tracker'!$B$10:$B$159,"<"&('📆 Current Week'!$M$9-0+7)) -> 0 | L23: 🗂️ Admin | M23: ='⚙️ Settings'!D31 -> 2.5
L24: 📈 Business Development | M24: ='⚙️ Settings'!D32 -> 4
B25: 💡 EXECUTIVE INSIGHTS | L25: 🎬 Content Creation | M25: ='⚙️ Settings'!D33 -> 6
B26: ="🏆 Largest planned investment: "&INDEX('⚙️ Settings'!$C$17:$C$38,MATCH(MAX('⚙️ Settings'!$D$17:$D$38),'⚙️ Settings'!$D$17:$D$38,0))&" ("&TEXT(MAX('⚙️ Settings'!$D$17:$D$38),"0.0")&" h/week)" -> 🏆 Largest planned investment: Sleep (57.2 h/week) | L26: ✅ Free Time | M26: =MAX(0,'⚙️ Settings'!$D$41) -> 11.25
B27: =IF(SUM('📆 Current Week'!$F$12:$F$33)=0,"📅 Log your first day on the Daily Tracker to unlock live insights.",IF(MAX('📆 Current Week'!$G$12:$G$33)<=0,"✅ No category is over plan this week.","🔺 Most over plan this week: "&INDEX('⚙️ Settings'!$C$17:$C$38,MATCH(MAX('📆 Current Week'!$G$12:$G$33),'📆 Current Week'!$G$12:$G$33,0))&" (+"&TEXT(MAX('📆 Current Week'!$G$12:$G$33),"0.0")&" h)")) -> 📅 Log your first day on the Daily Tracker to unlock live insights. | L27: =IF('⚙️ Settings'!C34="","",'⚙️ Settings'!B34&" "&'⚙️ Settings'!C34) | M27: =IF('⚙️ Settings'!C34="","",'⚙️ Settings'!D34)
B28: =IF(SUM('📆 Current Week'!$F$12:$F$33)=0,"","🔻 Most behind plan this week: "&INDEX('⚙️ Settings'!$C$17:$C$38,MATCH(MIN('📆 Current Week'!$G$12:$G$33),'📆 Current Week'!$G$12:$G$33,0))&" ("&TEXT(MIN('📆 Current Week'!$G$12:$G$33),"0.0")&" h)") | L28: =IF('⚙️ Settings'!C35="","",'⚙️ Settings'!B35&" "&'⚙️ Settings'!C35) | M28: =IF('⚙️ Settings'!C35="","",'⚙️ Settings'!D35)
L29: =IF('⚙️ Settings'!C36="","",'⚙️ Settings'!B36&" "&'⚙️ Settings'!C36) | M29: =IF('⚙️ Settings'!C36="","",'⚙️ Settings'!D36)
L30: =IF('⚙️ Settings'!C37="","",'⚙️ Settings'!B37&" "&'⚙️ Settings'!C37) | M30: =IF('⚙️ Settings'!C37="","",'⚙️ Settings'!D37)
L31: =IF('⚙️ Settings'!C38="","",'⚙️ Settings'!B38&" "&'⚙️ Settings'!C38) | M31: =IF('⚙️ Settings'!C38="","",'⚙️ Settings'!D38)
L32: ❌ Total Non-Free Time | M32: ='⚙️ Settings'!$D$40 -> 156.75

Sheet 📖 Start Here
B2: 📖 Start Here — how to run ASCENSION OS™
B4: 🧭 THE OPERATING SYSTEM
C5: Everyone gets 24 hours a day and 168 hours a week. ASCENSION OS™ treats them like a budget: design on 🌟 Ideal Week, commit on 📆 Current Week, execute on 📅 Daily Tracker — every dashboard and review reconciles automatically.
C6: Every sheet carries the same executive KPI strip on top, plus a live line of what you logged today / this week / this month / this year — no tab switching needed to know where you stand.
B8: ✏️ RULE #1 — ONLY EDIT LIGHT-BLUE CELLS
C9: Every editable cell has a light-blue background. Everything else is a formula.
B11: 🚀 THE OPERATING LOOP
C12: 1. DESIGN — answer the guided sentences on 🌟 Ideal Week.
C13: 2. COMMIT — on 📆 Current Week, optionally override any category for this week ("My plan"). Blank = ideal.
C14: 3. EXECUTE — log real blocks on 📅 Daily Tracker: date, category (dropdown), hours, notes. The Today panel scores your day live.
C15: 4. REVIEW — 🗓️ Monthly Review and 🎯 Annual Review build themselves. 📊 Dashboard is the command centre.
B17: ➕ CUSTOM CATEGORIES & GOALS
C18: Add categories in the blue rows at the bottom of the ⚙️ Settings master table.
C19: Work days, sleep goal and your weekly productive target also live on ⚙️ Settings.
B21: 🎯 BALANCE SCORE
C22: A 0–100 gauge: sleep at goal, total work (work + deep work + meetings) ≤ 55 h, fitness ≥ 3 h, relationships ≥ 3 h, learning + personal development ≥ 2 h, free time ≥ 5 h, nothing over-allocated. 80+ = sustainable.
B24: 📐 ASSUMPTIONS
C25: Monthly = weekly × 4, yearly = weekly × 52 (editable on ⚙️ Settings; use 4.345 / 52.18 for calendar-accurate maths).
C26: The week runs Monday–Sunday. The Daily Tracker holds 150 log rows — clear old rows when you start a fresh period.
